[
  {
    "id": "4221644177",
    "site": "theqoo",
    "title": "대소변에 뭉친 털만 7kg…서귀포 ‘쓰레기’ 빌라서 구조된 개",
    "url": "https://theqoo.net/square/4221644177",
    "thumb": null,
    "score": 794,
    "views": null,
    "crawled_at": "2026-05-29T02:42:00.699962+00:00"
  },
  {
    "id": "4221642112",
    "site": "theqoo",
    "title": "효녀가 되고자 하나 현실이 돕지 않는다",
    "url": "https://theqoo.net/square/4221642112",
    "thumb": null,
    "score": 723,
    "views": null,
    "crawled_at": "2026-05-29T02:42:00.699962+00:00"
  },
  {
    "id": "4221645662",
    "site": "theqoo",
    "title": "네이버페이 15원이오",
    "url": "https://theqoo.net/square/4221645662",
    "thumb": null,
    "score": 663,
    "views": null,
    "crawled_at": "2026-05-29T02:42:00.699962+00:00"
  },
  {
    "id": "4221647673",
    "site": "theqoo",
    "title": "진돌&히디 <만달로리안과 그로구>리뷰",
    "url": "https://theqoo.net/square/4221647673",
    "thumb": null,
    "score": 453,
    "views": null,
    "crawled_at": "2026-05-29T02:42:00.699962+00:00"
  },
  {
    "id": "4221650449",
    "site": "theqoo",
    "title": "네? 뭘 허위 통보를 했다고요?",
    "url": "https://theqoo.net/square/4221650449",
    "thumb": null,
    "score": 441,
    "views": null,
    "crawled_at": "2026-05-29T02:42:00.699962+00:00"
  },
  {
    "id": "4221642786",
    "site": "theqoo",
    "title": "동생 등록님 내주는 itzy 채령이",
    "url": "https://theqoo.net/square/4221642786",
    "thumb": null,
    "score": 362,
    "views": null,
    "crawled_at": "2026-05-29T02:42:00.699962+00:00"
  },
  {
    "id": "4221647475",
    "site": "theqoo",
    "title": "야구장에 치어리더 배우러 갔다가 카감과 혼열일체가 된 이준",
    "url": "https://theqoo.net/square/4221647475",
    "thumb": null,
    "score": 294,
    "views": null,
    "crawled_at": "2026-05-29T02:42:00.699962+00:00"
  },
  {
    "id": "4221641607",
    "site": "theqoo",
    "title": "[먼작귀] 오늘 일본방영한 털 자른 치이카와 에피소드 2탄",
    "url": "https://theqoo.net/square/4221641607",
    "thumb": null,
    "score": 291,
    "views": null,
    "crawled_at": "2026-05-29T02:42:00.699962+00:00"
  },
  {
    "id": "4221646660",
    "site": "theqoo",
    "title": "아이오아이 ioi 멜론 탑백 추이",
    "url": "https://theqoo.net/square/4221646660",
    "thumb": null,
    "score": 255,
    "views": null,
    "crawled_at": "2026-05-29T02:42:00.699962+00:00"
  },
  {
    "id": "4221644010",
    "site": "theqoo",
    "title": "오승환, “현장에서 보니 너무 재미있다”…야구 꿈나무와 4라운드 동행",
    "url": "https://theqoo.net/square/4221644010",
    "thumb": null,
    "score": 246,
    "views": null,
    "crawled_at": "2026-05-29T02:42:00.699962+00:00"
  },
  {
    "id": "4221641747",
    "site": "theqoo",
    "title": "이준영·인피니트·정은지 등 소속사 빌리언스, 악플러 국내·외 '민·형사' 법대응 확대 [공식]",
    "url": "https://theqoo.net/square/4221641747",
    "thumb": null,
    "score": 224,
    "views": null,
    "crawled_at": "2026-05-29T02:42:00.699962+00:00"
  },
  {
    "id": "4221643129",
    "site": "theqoo",
    "title": "신현준 “‘천국의 계단’ 역변설? 엄마도 이해 못 해” (전현무계획3)",
    "url": "https://theqoo.net/square/4221643129",
    "thumb": null,
    "score": 219,
    "views": null,
    "crawled_at": "2026-05-29T02:42:00.699962+00:00"
  },
  {
    "id": "4221648889",
    "site": "theqoo",
    "title": "[멋진 신세계] 본격 차세계 헌정 영상😏 이 영상 제일 좋아할 사람=차세계",
    "url": "https://theqoo.net/square/4221648889",
    "thumb": null,
    "score": 211,
    "views": null,
    "crawled_at": "2026-05-29T02:42:00.699962+00:00"
  },
  {
    "id": "4221648283",
    "site": "theqoo",
    "title": "5/31 이번주 인기가요 라인업",
    "url": "https://theqoo.net/square/4221648283",
    "thumb": null,
    "score": 183,
    "views": null,
    "crawled_at": "2026-05-29T02:42:00.699962+00:00"
  },
  {
    "id": "4221646501",
    "site": "theqoo",
    "title": "30년전 마이클잭슨이 공연했던 스타디움에서 영화 마이클 상영회 하는 러시아",
    "url": "https://theqoo.net/square/4221646501",
    "thumb": null,
    "score": 133,
    "views": null,
    "crawled_at": "2026-05-29T02:42:00.699962+00:00"
  },
  {
    "id": "4221647602",
    "site": "theqoo",
    "title": "나홍진 ‘호프’, 200여 개국 선판매…한국 영화 역대 최고가",
    "url": "https://theqoo.net/square/4221647602",
    "thumb": null,
    "score": 104,
    "views": null,
    "crawled_at": "2026-05-29T02:42:00.699962+00:00"
  },
  {
    "id": "300143",
    "site": "ruliweb",
    "title": "속보) 클럽에서 여자 분이랑 인스타 아이디, 전화번호 교환한 후기(2)",
    "url": "https://bbs.ruliweb.com/community/board/300143/read/75362601?",
    "thumb": null,
    "score": 2,
    "views": 75,
    "crawled_at": "2026-05-29T02:42:00.699962+00:00"
  },
  {
    "id": "300143",
    "site": "ruliweb",
    "title": "무리무리) 생일선물 받아내는 여동생(1)",
    "url": "https://bbs.ruliweb.com/community/board/300143/read/75362600?",
    "thumb": null,
    "score": 2,
    "views": 47,
    "crawled_at": "2026-05-29T02:42:00.699962+00:00"
  },
  {
    "id": "300143",
    "site": "ruliweb",
    "title": "1957년 B-52 폭격기 5대가 캘리포니아 기지에서 출동한 이유.(1)",
    "url": "https://bbs.ruliweb.com/community/board/300143/read/75362592?",
    "thumb": null,
    "score": 2,
    "views": 93,
    "crawled_at": "2026-05-29T02:42:00.699962+00:00"
  },
  {
    "id": "9954287",
    "site": "ppomppu",
    "title": "사전투표 반대론자들이 충격받을 뉴스",
    "url": "https://www.ppomppu.co.kr/zboard/view.php?id=freeboard&page=1&divpage=1859&no=9954287",
    "thumb": null,
    "score": 2,
    "views": null,
    "crawled_at": "2026-05-29T02:42:00.699962+00:00"
  },
  {
    "id": "9954276",
    "site": "ppomppu",
    "title": "이명박 개새 부산에 왔다고 좋아하는 부산 사람들은 저능아들임.",
    "url": "https://www.ppomppu.co.kr/zboard/view.php?id=freeboard&page=1&divpage=1859&no=9954276",
    "thumb": null,
    "score": 2,
    "views": null,
    "crawled_at": "2026-05-29T02:42:00.699962+00:00"
  },
  {
    "id": "100647",
    "site": "ruliweb",
    "title": "시즌 배달 미션 완료 어떻게하나요",
    "url": "https://bbs.ruliweb.com/etcs/board/100647/read/9426324",
    "thumb": null,
    "score": 1,
    "views": 143,
    "crawled_at": "2026-05-29T02:42:00.699962+00:00"
  },
  {
    "id": "300143",
    "site": "ruliweb",
    "title": "림버스) 아 서버 얽힘 진짜",
    "url": "https://bbs.ruliweb.com/community/board/300143/read/75362599?",
    "thumb": null,
    "score": 1,
    "views": 14,
    "crawled_at": "2026-05-29T02:42:00.699962+00:00"
  },
  {
    "id": "300143",
    "site": "ruliweb",
    "title": "니케) 크으으으으 이것이 애증보빔 크으으으(스포있음)",
    "url": "https://bbs.ruliweb.com/community/board/300143/read/75362594?",
    "thumb": null,
    "score": 1,
    "views": 53,
    "crawled_at": "2026-05-29T02:42:00.699962+00:00"
  },
  {
    "id": "9954284",
    "site": "ppomppu",
    "title": "타이어 바꾸니 느낌이 달라지긴하네여",
    "url": "https://www.ppomppu.co.kr/zboard/view.php?id=freeboard&page=1&divpage=1859&no=9954284",
    "thumb": null,
    "score": 1,
    "views": null,
    "crawled_at": "2026-05-29T02:42:00.699962+00:00"
  },
  {
    "id": "9954277",
    "site": "ppomppu",
    "title": "투표 완료",
    "url": "https://www.ppomppu.co.kr/zboard/view.php?id=freeboard&page=1&divpage=1859&no=9954277",
    "thumb": null,
    "score": 1,
    "views": null,
    "crawled_at": "2026-05-29T02:42:00.699962+00:00"
  },
  {
    "id": "300142",
    "site": "ruliweb",
    "title": "갤럭시 무선충전 qi에 대한 질문입니다",
    "url": "https://bbs.ruliweb.com/community/board/300142/read/30619473",
    "thumb": null,
    "score": 0,
    "views": 1490,
    "crawled_at": "2026-05-29T02:42:00.699962+00:00"
  },
  {
    "id": "184778",
    "site": "ruliweb",
    "title": "보호장구 30강 강화후 프로토변환시 2꽉 뜨나요?",
    "url": "https://bbs.ruliweb.com/etcs/board/184778/read/107091",
    "thumb": null,
    "score": 0,
    "views": 263,
    "crawled_at": "2026-05-29T02:42:00.699962+00:00"
  },
  {
    "id": "300143",
    "site": "ruliweb",
    "title": "아이브 가을",
    "url": "https://bbs.ruliweb.com/community/board/300143/read/75362608?",
    "thumb": null,
    "score": 0,
    "views": 5,
    "crawled_at": "2026-05-29T02:42:00.699962+00:00"
  },
  {
    "id": "300143",
    "site": "ruliweb",
    "title": "삼중 스파이가 잠입한 조직에서 여사친 만나 찌찌 만지는 애니.jpg",
    "url": "https://bbs.ruliweb.com/community/board/300143/read/75362607?",
    "thumb": null,
    "score": 0,
    "views": 3,
    "crawled_at": "2026-05-29T02:42:00.699962+00:00"
  },
  {
    "id": "300143",
    "site": "ruliweb",
    "title": "오늘 날 팔로우한 트위터가 수상하다...",
    "url": "https://bbs.ruliweb.com/community/board/300143/read/75362606?",
    "thumb": null,
    "score": 0,
    "views": 16,
    "crawled_at": "2026-05-29T02:42:00.699962+00:00"
  },
  {
    "id": "300143",
    "site": "ruliweb",
    "title": "주식) 아 네이버클라우드도 투자 대상이구나",
    "url": "https://bbs.ruliweb.com/community/board/300143/read/75362605?",
    "thumb": null,
    "score": 0,
    "views": 15,
    "crawled_at": "2026-05-29T02:42:00.699962+00:00"
  },
  {
    "id": "300143",
    "site": "ruliweb",
    "title": "명조) 오늘 공방에서 에이메스 복각 말해주면 좋겠다(1)",
    "url": "https://bbs.ruliweb.com/community/board/300143/read/75362604?",
    "thumb": null,
    "score": 0,
    "views": 10,
    "crawled_at": "2026-05-29T02:42:00.699962+00:00"
  },
  {
    "id": "300143",
    "site": "ruliweb",
    "title": "림버스)확실히 응룡은 검지침잠이 편한듯",
    "url": "https://bbs.ruliweb.com/community/board/300143/read/75362603?",
    "thumb": null,
    "score": 0,
    "views": 11,
    "crawled_at": "2026-05-29T02:42:00.699962+00:00"
  },
  {
    "id": "300143",
    "site": "ruliweb",
    "title": "림버스) 이번 거굴철이 특히 더 느린가",
    "url": "https://bbs.ruliweb.com/community/board/300143/read/75362602?",
    "thumb": null,
    "score": 0,
    "views": 8,
    "crawled_at": "2026-05-29T02:42:00.699962+00:00"
  },
  {
    "id": "300143",
    "site": "ruliweb",
    "title": "모바일게임에서 한정만 낸다고 까는거 이해 못함",
    "url": "https://bbs.ruliweb.com/community/board/300143/read/75362598?",
    "thumb": null,
    "score": 0,
    "views": 65,
    "crawled_at": "2026-05-29T02:42:00.699962+00:00"
  },
  {
    "id": "300143",
    "site": "ruliweb",
    "title": "블루아카) 우이 히나타 만화는 이게 봐도봐도 최고임",
    "url": "https://bbs.ruliweb.com/community/board/300143/read/75362597?",
    "thumb": null,
    "score": 0,
    "views": 73,
    "crawled_at": "2026-05-29T02:42:00.699962+00:00"
  },
  {
    "id": "300143",
    "site": "ruliweb",
    "title": "마운자로 고민 중인데 병원마다 차이가 꽤 있네요(1)",
    "url": "https://bbs.ruliweb.com/community/board/300143/read/75362596?",
    "thumb": null,
    "score": 0,
    "views": 39,
    "crawled_at": "2026-05-29T02:42:00.699962+00:00"
  },
  {
    "id": "300143",
    "site": "ruliweb",
    "title": "뭔가 이상한 웰시코기 달리기 대회(1)",
    "url": "https://bbs.ruliweb.com/community/board/300143/read/75362595?",
    "thumb": null,
    "score": 0,
    "views": 86,
    "crawled_at": "2026-05-29T02:42:00.699962+00:00"
  },
  {
    "id": "300143",
    "site": "ruliweb",
    "title": "블루아카)공략안보고 1팟클 할려니 빡세네",
    "url": "https://bbs.ruliweb.com/community/board/300143/read/75362593?",
    "thumb": null,
    "score": 0,
    "views": 20,
    "crawled_at": "2026-05-29T02:42:00.699962+00:00"
  },
  {
    "id": "3836786021",
    "site": "theqoo",
    "title": "[스퀘어게시판 정치 카테고리 추가 및 정치 제외 기능 추가]",
    "url": "https://theqoo.net/square/3836786021",
    "thumb": null,
    "score": 0,
    "views": null,
    "crawled_at": "2026-05-29T02:42:00.699962+00:00"
  },
  {
    "id": "1638396273",
    "site": "theqoo",
    "title": "나는 더쿠에서 움짤을 한 번이라도 올려본 적이 있다 🙋‍♀️",
    "url": "https://theqoo.net/square/1638396273",
    "thumb": null,
    "score": 0,
    "views": null,
    "crawled_at": "2026-05-29T02:42:00.699962+00:00"
  },
  {
    "id": "1419228502",
    "site": "theqoo",
    "title": "더쿠에 쉽게 동영상을 올려보자 !",
    "url": "https://theqoo.net/square/1419228502",
    "thumb": null,
    "score": 0,
    "views": null,
    "crawled_at": "2026-05-29T02:42:00.699962+00:00"
  },
  {
    "id": "1386342829",
    "site": "theqoo",
    "title": "슬기로운 더쿠생활 : 더쿠 이용팁",
    "url": "https://theqoo.net/square/1386342829",
    "thumb": null,
    "score": 0,
    "views": null,
    "crawled_at": "2026-05-29T02:42:00.699962+00:00"
  },
  {
    "id": "9954294",
    "site": "ppomppu",
    "title": "부산 북구 주민 여러분",
    "url": "https://www.ppomppu.co.kr/zboard/view.php?id=freeboard&page=1&divpage=1859&no=9954294",
    "thumb": null,
    "score": 0,
    "views": null,
    "crawled_at": "2026-05-29T02:42:00.699962+00:00"
  },
  {
    "id": "9954293",
    "site": "ppomppu",
    "title": "오늘은 전국 지방/재보궐 선거 투표 날입니다",
    "url": "https://www.ppomppu.co.kr/zboard/view.php?id=freeboard&page=1&divpage=1859&no=9954293",
    "thumb": null,
    "score": 0,
    "views": null,
    "crawled_at": "2026-05-29T02:42:00.699962+00:00"
  },
  {
    "id": "9954292",
    "site": "ppomppu",
    "title": "당x마켓 갈수록  불편마켓 되는것 같아요",
    "url": "https://www.ppomppu.co.kr/zboard/view.php?id=freeboard&page=1&divpage=1859&no=9954292",
    "thumb": null,
    "score": 0,
    "views": null,
    "crawled_at": "2026-05-29T02:42:00.699962+00:00"
  },
  {
    "id": "9954291",
    "site": "ppomppu",
    "title": "사전투표 완료",
    "url": "https://www.ppomppu.co.kr/zboard/view.php?id=freeboard&page=1&divpage=1859&no=9954291",
    "thumb": null,
    "score": 0,
    "views": null,
    "crawled_at": "2026-05-29T02:42:00.699962+00:00"
  },
  {
    "id": "9954290",
    "site": "ppomppu",
    "title": "거제도에서 최초로 포획된 자이언트 트레발리..jpg",
    "url": "https://www.ppomppu.co.kr/zboard/view.php?id=freeboard&page=1&divpage=1859&no=9954290",
    "thumb": null,
    "score": 0,
    "views": null,
    "crawled_at": "2026-05-29T02:42:00.699962+00:00"
  },
  {
    "id": "9954289",
    "site": "ppomppu",
    "title": "\"민주당 후보가 그랬다니.. 망지소조()에 빠진 진도 민심",
    "url": "https://www.ppomppu.co.kr/zboard/view.php?id=freeboard&page=1&divpage=1859&no=9954289",
    "thumb": null,
    "score": 0,
    "views": null,
    "crawled_at": "2026-05-29T02:42:00.699962+00:00"
  },
  {
    "id": "9954288",
    "site": "ppomppu",
    "title": "사전 투표 완료",
    "url": "https://www.ppomppu.co.kr/zboard/view.php?id=freeboard&page=1&divpage=1859&no=9954288",
    "thumb": null,
    "score": 0,
    "views": null,
    "crawled_at": "2026-05-29T02:42:00.699962+00:00"
  },
  {
    "id": "9954286",
    "site": "ppomppu",
    "title": "요즘 스벅",
    "url": "https://www.ppomppu.co.kr/zboard/view.php?id=freeboard&page=1&divpage=1859&no=9954286",
    "thumb": null,
    "score": 0,
    "views": null,
    "crawled_at": "2026-05-29T02:42:00.699962+00:00"
  },
  {
    "id": "9954285",
    "site": "ppomppu",
    "title": "베트남 다낭도 이제 아예 대놓고 팁을 달라고 하네요,,예전 다낭이 아닌듯",
    "url": "https://www.ppomppu.co.kr/zboard/view.php?id=freeboard&page=1&divpage=1859&no=9954285",
    "thumb": null,
    "score": 0,
    "views": null,
    "crawled_at": "2026-05-29T02:42:00.699962+00:00"
  },
  {
    "id": "9954283",
    "site": "ppomppu",
    "title": "사전투표하는 이재용 회장",
    "url": "https://www.ppomppu.co.kr/zboard/view.php?id=freeboard&page=1&divpage=1859&no=9954283",
    "thumb": null,
    "score": 0,
    "views": null,
    "crawled_at": "2026-05-29T02:42:00.699962+00:00"
  },
  {
    "id": "9954282",
    "site": "ppomppu",
    "title": "Ssg 9연패네요 ㄷㄷ",
    "url": "https://www.ppomppu.co.kr/zboard/view.php?id=freeboard&page=1&divpage=1859&no=9954282",
    "thumb": null,
    "score": 0,
    "views": null,
    "crawled_at": "2026-05-29T02:42:00.699962+00:00"
  },
  {
    "id": "9954281",
    "site": "ppomppu",
    "title": "캠핑은 언제까지 다닐 수 있나요",
    "url": "https://www.ppomppu.co.kr/zboard/view.php?id=freeboard&page=1&divpage=1859&no=9954281",
    "thumb": null,
    "score": 0,
    "views": null,
    "crawled_at": "2026-05-29T02:42:00.699962+00:00"
  },
  {
    "id": "9954280",
    "site": "ppomppu",
    "title": "토스 페이스페이 신박하네요 ㅎ",
    "url": "https://www.ppomppu.co.kr/zboard/view.php?id=freeboard&page=1&divpage=1859&no=9954280",
    "thumb": null,
    "score": 0,
    "views": null,
    "crawled_at": "2026-05-29T02:42:00.699962+00:00"
  },
  {
    "id": "9954279",
    "site": "ppomppu",
    "title": "김민새는 뭘 믿고 저러나요?",
    "url": "https://www.ppomppu.co.kr/zboard/view.php?id=freeboard&page=1&divpage=1859&no=9954279",
    "thumb": null,
    "score": 0,
    "views": null,
    "crawled_at": "2026-05-29T02:42:00.699962+00:00"
  },
  {
    "id": "9954278",
    "site": "ppomppu",
    "title": "오늘도 코스피는 빨갛네요..",
    "url": "https://www.ppomppu.co.kr/zboard/view.php?id=freeboard&page=1&divpage=1859&no=9954278",
    "thumb": null,
    "score": 0,
    "views": null,
    "crawled_at": "2026-05-29T02:42:00.699962+00:00"
  },
  {
    "id": "9954275",
    "site": "ppomppu",
    "title": "인천 현직 경찰관 만취 운전 추돌사고, 직위 해제",
    "url": "https://www.ppomppu.co.kr/zboard/view.php?id=freeboard&page=1&divpage=1859&no=9954275",
    "thumb": null,
    "score": 0,
    "views": null,
    "crawled_at": "2026-05-29T02:42:00.699962+00:00"
  }
]