[
  {
    "id": "4199194886",
    "site": "theqoo",
    "title": "<취사병 전설이 되다> 첫방 시청률",
    "url": "https://theqoo.net/square/4199194886",
    "thumb": null,
    "score": 2277,
    "views": null,
    "crawled_at": "2026-05-11T22:49:23.782562+00:00"
  },
  {
    "id": "4199191472",
    "site": "theqoo",
    "title": "[단독] 성추행 가해자가 학폭 맞신고…80%가 이렇게 징계 뒤집었다",
    "url": "https://theqoo.net/square/4199191472",
    "thumb": null,
    "score": 1762,
    "views": null,
    "crawled_at": "2026-05-11T22:49:23.782562+00:00"
  },
  {
    "id": "4199191251",
    "site": "theqoo",
    "title": "김동완 “‘8번 이혼’ 유퉁, 함부로 논하면 안 돼” 소신 발언",
    "url": "https://theqoo.net/square/4199191251",
    "thumb": null,
    "score": 1757,
    "views": null,
    "crawled_at": "2026-05-11T22:49:23.782562+00:00"
  },
  {
    "id": "4199190437",
    "site": "theqoo",
    "title": "공사 강행해서 완공된 서울시 광화문광장 감사의정원 및 야간조명",
    "url": "https://theqoo.net/square/4199190437",
    "thumb": null,
    "score": 1476,
    "views": null,
    "crawled_at": "2026-05-11T22:49:23.782562+00:00"
  },
  {
    "id": "4199194045",
    "site": "theqoo",
    "title": "일일카페 알바 직원 비주얼 때문에 난리난 팬싸 근황",
    "url": "https://theqoo.net/square/4199194045",
    "thumb": null,
    "score": 1271,
    "views": null,
    "crawled_at": "2026-05-11T22:49:23.782562+00:00"
  },
  {
    "id": "4199190942",
    "site": "theqoo",
    "title": "2026 한국 소득 계층 (4인 기준)",
    "url": "https://theqoo.net/square/4199190942",
    "thumb": null,
    "score": 1214,
    "views": null,
    "crawled_at": "2026-05-11T22:49:23.782562+00:00"
  },
  {
    "id": "4199190714",
    "site": "theqoo",
    "title": "\"월세 20만원 지원\" 착한 정책 내놨더니…'놀라운 반전'",
    "url": "https://theqoo.net/square/4199190714",
    "thumb": null,
    "score": 1208,
    "views": null,
    "crawled_at": "2026-05-11T22:49:23.782562+00:00"
  },
  {
    "id": "4199200279",
    "site": "theqoo",
    "title": "소름인게 하닉 이 때만 샀어도 이득이었음",
    "url": "https://theqoo.net/square/4199200279",
    "thumb": null,
    "score": 1153,
    "views": null,
    "crawled_at": "2026-05-11T22:49:23.782562+00:00"
  },
  {
    "id": "4199199502",
    "site": "theqoo",
    "title": "미국인이 말하는 진돗개 의외의 단점",
    "url": "https://theqoo.net/square/4199199502",
    "thumb": null,
    "score": 670,
    "views": null,
    "crawled_at": "2026-05-11T22:49:23.782562+00:00"
  },
  {
    "id": "4199195500",
    "site": "theqoo",
    "title": "영화 와일드씽 강동원(황현우) 스틸컷❤️",
    "url": "https://theqoo.net/square/4199195500",
    "thumb": null,
    "score": 614,
    "views": null,
    "crawled_at": "2026-05-11T22:49:23.782562+00:00"
  },
  {
    "id": "4199198121",
    "site": "theqoo",
    "title": "결혼 이어 운동도 그들끼리…반포·잠원 초고가 아파트 스포츠 '맞대결'",
    "url": "https://theqoo.net/square/4199198121",
    "thumb": null,
    "score": 423,
    "views": null,
    "crawled_at": "2026-05-11T22:49:23.782562+00:00"
  },
  {
    "id": "4199200064",
    "site": "theqoo",
    "title": "“잘 지내고 있다” 인터뷰 거절…보호대 찬 나무호 선원, 눈 주위엔 멍까지",
    "url": "https://theqoo.net/square/4199200064",
    "thumb": null,
    "score": 417,
    "views": null,
    "crawled_at": "2026-05-11T22:49:23.782562+00:00"
  },
  {
    "id": "4199201846",
    "site": "theqoo",
    "title": "엄마! 친구들 중에 내가 제일 못생겼어...",
    "url": "https://theqoo.net/square/4199201846",
    "thumb": null,
    "score": 323,
    "views": null,
    "crawled_at": "2026-05-11T22:49:23.782562+00:00"
  },
  {
    "id": "4199189659",
    "site": "theqoo",
    "title": "공격 비행체는 중형급?‥靑 \"민간 공격 강력규탄\"",
    "url": "https://theqoo.net/square/4199189659",
    "thumb": null,
    "score": 212,
    "views": null,
    "crawled_at": "2026-05-11T22:49:23.782562+00:00"
  },
  {
    "id": "4199188263",
    "site": "theqoo",
    "title": "우타다 히카루 「Flavor Of Life-Ballad Version」최신 음악 방송 라이브",
    "url": "https://theqoo.net/square/4199188263",
    "thumb": null,
    "score": 199,
    "views": null,
    "crawled_at": "2026-05-11T22:49:23.782562+00:00"
  },
  {
    "id": "4199196787",
    "site": "theqoo",
    "title": "신한플러스/플레이 정답",
    "url": "https://theqoo.net/square/4199196787",
    "thumb": null,
    "score": 97,
    "views": null,
    "crawled_at": "2026-05-11T22:49:23.782562+00:00"
  },
  {
    "id": "300143",
    "site": "ruliweb",
    "title": "일본에서 일어난 이란 전쟁의 여파(3)",
    "url": "https://bbs.ruliweb.com/community/board/300143/read/75148699?",
    "thumb": null,
    "score": 18,
    "views": 1214,
    "crawled_at": "2026-05-11T22:49:23.782562+00:00"
  },
  {
    "id": "9934999",
    "site": "ppomppu",
    "title": "윤석열과 공범기자들의 엽기적인 영상~",
    "url": "https://www.ppomppu.co.kr/zboard/view.php?id=freeboard&page=1&divpage=1855&no=9934999",
    "thumb": null,
    "score": 11,
    "views": null,
    "crawled_at": "2026-05-11T22:49:23.782562+00:00"
  },
  {
    "id": "300143",
    "site": "ruliweb",
    "title": "어이구 우리 소중한 아이 심사를 해야한다고?(4)",
    "url": "https://bbs.ruliweb.com/community/board/300143/read/75148703?",
    "thumb": null,
    "score": 4,
    "views": 114,
    "crawled_at": "2026-05-11T22:49:23.782562+00:00"
  },
  {
    "id": "9934991",
    "site": "ppomppu",
    "title": "조국. 일 잘하네",
    "url": "https://www.ppomppu.co.kr/zboard/view.php?id=freeboard&page=1&divpage=1855&no=9934991",
    "thumb": null,
    "score": 4,
    "views": null,
    "crawled_at": "2026-05-11T22:49:23.782562+00:00"
  },
  {
    "id": "9934987",
    "site": "ppomppu",
    "title": "곱버스 지인.",
    "url": "https://www.ppomppu.co.kr/zboard/view.php?id=freeboard&page=1&divpage=1855&no=9934987",
    "thumb": null,
    "score": 2,
    "views": null,
    "crawled_at": "2026-05-11T22:49:23.782562+00:00"
  },
  {
    "id": "300143",
    "site": "ruliweb",
    "title": "블루아카) 좋은데 표정관리 하는 아코",
    "url": "https://bbs.ruliweb.com/community/board/300143/read/75148714?",
    "thumb": null,
    "score": 1,
    "views": 10,
    "crawled_at": "2026-05-11T22:49:23.782562+00:00"
  },
  {
    "id": "300143",
    "site": "ruliweb",
    "title": "다시 봐도 매콤하다 못해 얼얼하기까지 한 동화.jpg(1)",
    "url": "https://bbs.ruliweb.com/community/board/300143/read/75148706?",
    "thumb": null,
    "score": 1,
    "views": 82,
    "crawled_at": "2026-05-11T22:49:23.782562+00:00"
  },
  {
    "id": "300143",
    "site": "ruliweb",
    "title": "블루아카) ??: 거참 문잠근다고 해결 안된다니깐(2)",
    "url": "https://bbs.ruliweb.com/community/board/300143/read/75148700?",
    "thumb": null,
    "score": 1,
    "views": 90,
    "crawled_at": "2026-05-11T22:49:23.782562+00:00"
  },
  {
    "id": "9935000",
    "site": "ppomppu",
    "title": "'쿠팡 개인정보 유출' 조사 마무리 이르면 6월 결론 나온다",
    "url": "https://www.ppomppu.co.kr/zboard/view.php?id=freeboard&page=1&divpage=1855&no=9935000",
    "thumb": null,
    "score": 1,
    "views": null,
    "crawled_at": "2026-05-11T22:49:23.782562+00:00"
  },
  {
    "id": "9934998",
    "site": "ppomppu",
    "title": "근데 내란전담재판부 판사들 유죄주면 죽을까봐 무서워서",
    "url": "https://www.ppomppu.co.kr/zboard/view.php?id=freeboard&page=1&divpage=1855&no=9934998",
    "thumb": null,
    "score": 1,
    "views": null,
    "crawled_at": "2026-05-11T22:49:23.782562+00:00"
  },
  {
    "id": "9934995",
    "site": "ppomppu",
    "title": "은행방문 저만 불편한가요? 지점 줄이는거 정말 정부가 손 봐줬으면 좋겠네요.",
    "url": "https://www.ppomppu.co.kr/zboard/view.php?id=freeboard&page=1&divpage=1855&no=9934995",
    "thumb": null,
    "score": 1,
    "views": null,
    "crawled_at": "2026-05-11T22:49:23.782562+00:00"
  },
  {
    "id": "300142",
    "site": "ruliweb",
    "title": "새로 구입한 란쿨 216 케이스 화이트 소음(드르르륵?) 해결법 아시는 ...",
    "url": "https://bbs.ruliweb.com/community/board/300142/read/30619415",
    "thumb": null,
    "score": 0,
    "views": 163,
    "crawled_at": "2026-05-11T22:49:23.782562+00:00"
  },
  {
    "id": "186188",
    "site": "ruliweb",
    "title": "안녕하세요 시작한지 일주일정도 된 뉴비 입니다",
    "url": "https://bbs.ruliweb.com/etcs/board/186188/read/2433",
    "thumb": null,
    "score": 0,
    "views": 128,
    "crawled_at": "2026-05-11T22:49:23.782562+00:00"
  },
  {
    "id": "184137",
    "site": "ruliweb",
    "title": "스토리즈3 혹시 도스가레오스 안나오나요??",
    "url": "https://bbs.ruliweb.com/etcs/board/184137/read/348790",
    "thumb": null,
    "score": 0,
    "views": 119,
    "crawled_at": "2026-05-11T22:49:23.782562+00:00"
  },
  {
    "id": "300143",
    "site": "ruliweb",
    "title": "임진왜란 조선의 반격 접음",
    "url": "https://bbs.ruliweb.com/community/board/300143/read/75148715?",
    "thumb": null,
    "score": 0,
    "views": 12,
    "crawled_at": "2026-05-11T22:49:23.782562+00:00"
  },
  {
    "id": "300143",
    "site": "ruliweb",
    "title": "림버스) 나 천잰가?",
    "url": "https://bbs.ruliweb.com/community/board/300143/read/75148713?",
    "thumb": null,
    "score": 0,
    "views": 12,
    "crawled_at": "2026-05-11T22:49:23.782562+00:00"
  },
  {
    "id": "300143",
    "site": "ruliweb",
    "title": "강남 경찰서 근황",
    "url": "https://bbs.ruliweb.com/community/board/300143/read/75148712?",
    "thumb": null,
    "score": 0,
    "views": 96,
    "crawled_at": "2026-05-11T22:49:23.782562+00:00"
  },
  {
    "id": "300143",
    "site": "ruliweb",
    "title": "마비m)음? 검방 리워크 각인가?",
    "url": "https://bbs.ruliweb.com/community/board/300143/read/75148711?",
    "thumb": null,
    "score": 0,
    "views": 11,
    "crawled_at": "2026-05-11T22:49:23.782562+00:00"
  },
  {
    "id": "300143",
    "site": "ruliweb",
    "title": "명조) 사펑 콜라보가 기대되는 이유",
    "url": "https://bbs.ruliweb.com/community/board/300143/read/75148710?",
    "thumb": null,
    "score": 0,
    "views": 32,
    "crawled_at": "2026-05-11T22:49:23.782562+00:00"
  },
  {
    "id": "300143",
    "site": "ruliweb",
    "title": "호프 내용 궁금하다",
    "url": "https://bbs.ruliweb.com/community/board/300143/read/75148709?",
    "thumb": null,
    "score": 0,
    "views": 16,
    "crawled_at": "2026-05-11T22:49:23.782562+00:00"
  },
  {
    "id": "300143",
    "site": "ruliweb",
    "title": "인천대공원쪽 사고 크게 났나보네(1)",
    "url": "https://bbs.ruliweb.com/community/board/300143/read/75148708?",
    "thumb": null,
    "score": 0,
    "views": 70,
    "crawled_at": "2026-05-11T22:49:23.782562+00:00"
  },
  {
    "id": "300143",
    "site": "ruliweb",
    "title": "스레드에서 화제인 이미지 컨설팅",
    "url": "https://bbs.ruliweb.com/community/board/300143/read/75148707?",
    "thumb": null,
    "score": 0,
    "views": 50,
    "crawled_at": "2026-05-11T22:49:23.782562+00:00"
  },
  {
    "id": "300143",
    "site": "ruliweb",
    "title": "으럇으럇마!!!",
    "url": "https://bbs.ruliweb.com/community/board/300143/read/75148705?",
    "thumb": null,
    "score": 0,
    "views": 47,
    "crawled_at": "2026-05-11T22:49:23.782562+00:00"
  },
  {
    "id": "300143",
    "site": "ruliweb",
    "title": "말딸) 스틸 스토리 특(1)",
    "url": "https://bbs.ruliweb.com/community/board/300143/read/75148704?",
    "thumb": null,
    "score": 0,
    "views": 29,
    "crawled_at": "2026-05-11T22:49:23.782562+00:00"
  },
  {
    "id": "300143",
    "site": "ruliweb",
    "title": "후방) 모닝글",
    "url": "https://bbs.ruliweb.com/community/board/300143/read/75148702?",
    "thumb": null,
    "score": 0,
    "views": 73,
    "crawled_at": "2026-05-11T22:49:23.782562+00:00"
  },
  {
    "id": "300143",
    "site": "ruliweb",
    "title": "주말에 배송온 日LP 새비닐 작업중",
    "url": "https://bbs.ruliweb.com/community/board/300143/read/75148701?",
    "thumb": null,
    "score": 0,
    "views": 53,
    "crawled_at": "2026-05-11T22:49:23.782562+00:00"
  },
  {
    "id": "3836786021",
    "site": "theqoo",
    "title": "[스퀘어게시판 정치 카테고리 추가 및 정치 제외 기능 추가]",
    "url": "https://theqoo.net/square/3836786021",
    "thumb": null,
    "score": 0,
    "views": null,
    "crawled_at": "2026-05-11T22:49:23.782562+00:00"
  },
  {
    "id": "1638396273",
    "site": "theqoo",
    "title": "나는 더쿠에서 움짤을 한 번이라도 올려본 적이 있다 🙋‍♀️",
    "url": "https://theqoo.net/square/1638396273",
    "thumb": null,
    "score": 0,
    "views": null,
    "crawled_at": "2026-05-11T22:49:23.782562+00:00"
  },
  {
    "id": "1419228502",
    "site": "theqoo",
    "title": "더쿠에 쉽게 동영상을 올려보자 !",
    "url": "https://theqoo.net/square/1419228502",
    "thumb": null,
    "score": 0,
    "views": null,
    "crawled_at": "2026-05-11T22:49:23.782562+00:00"
  },
  {
    "id": "1386342829",
    "site": "theqoo",
    "title": "슬기로운 더쿠생활 : 더쿠 이용팁",
    "url": "https://theqoo.net/square/1386342829",
    "thumb": null,
    "score": 0,
    "views": null,
    "crawled_at": "2026-05-11T22:49:23.782562+00:00"
  },
  {
    "id": "9935004",
    "site": "ppomppu",
    "title": "진에어, 승무원 입사 돌연 연기 통보 50여명 날벼락",
    "url": "https://www.ppomppu.co.kr/zboard/view.php?id=freeboard&page=1&divpage=1855&no=9935004",
    "thumb": null,
    "score": 0,
    "views": null,
    "crawled_at": "2026-05-11T22:49:23.782562+00:00"
  },
  {
    "id": "9935003",
    "site": "ppomppu",
    "title": "패밀리카로 꼭 SUV가 필요할까요",
    "url": "https://www.ppomppu.co.kr/zboard/view.php?id=freeboard&page=1&divpage=1855&no=9935003",
    "thumb": null,
    "score": 0,
    "views": null,
    "crawled_at": "2026-05-11T22:49:23.782562+00:00"
  },
  {
    "id": "9935002",
    "site": "ppomppu",
    "title": "강남3구 부모들이 자식들에게 가입시켜 주는거",
    "url": "https://www.ppomppu.co.kr/zboard/view.php?id=freeboard&page=1&divpage=1855&no=9935002",
    "thumb": null,
    "score": 0,
    "views": null,
    "crawled_at": "2026-05-11T22:49:23.782562+00:00"
  },
  {
    "id": "9935001",
    "site": "ppomppu",
    "title": "바닥에 걸린 한강 유람선, 한강버스 항로서 불과 100m 떨어졌다",
    "url": "https://www.ppomppu.co.kr/zboard/view.php?id=freeboard&page=1&divpage=1855&no=9935001",
    "thumb": null,
    "score": 0,
    "views": null,
    "crawled_at": "2026-05-11T22:49:23.782562+00:00"
  },
  {
    "id": "9934997",
    "site": "ppomppu",
    "title": "현재)난리난 한국 먹거리 음식 ㄷㄷ.jpg",
    "url": "https://www.ppomppu.co.kr/zboard/view.php?id=freeboard&page=1&divpage=1855&no=9934997",
    "thumb": null,
    "score": 0,
    "views": null,
    "crawled_at": "2026-05-11T22:49:23.782562+00:00"
  },
  {
    "id": "9934996",
    "site": "ppomppu",
    "title": "일교차에 감기 걸렸네용",
    "url": "https://www.ppomppu.co.kr/zboard/view.php?id=freeboard&page=1&divpage=1855&no=9934996",
    "thumb": null,
    "score": 0,
    "views": null,
    "crawled_at": "2026-05-11T22:49:23.782562+00:00"
  },
  {
    "id": "9934994",
    "site": "ppomppu",
    "title": "인간이 급격히 늙는 나이.jpg",
    "url": "https://www.ppomppu.co.kr/zboard/view.php?id=freeboard&page=1&divpage=1855&no=9934994",
    "thumb": null,
    "score": 0,
    "views": null,
    "crawled_at": "2026-05-11T22:49:23.782562+00:00"
  },
  {
    "id": "9934993",
    "site": "ppomppu",
    "title": "일본은 투자수익으로 버는 외화가 어마어마하네요ㄷㄷ",
    "url": "https://www.ppomppu.co.kr/zboard/view.php?id=freeboard&page=1&divpage=1855&no=9934993",
    "thumb": null,
    "score": 0,
    "views": null,
    "crawled_at": "2026-05-11T22:49:23.782562+00:00"
  },
  {
    "id": "9934992",
    "site": "ppomppu",
    "title": "현재)난리난 오늘자 미국주식 롤백사건 ㄷㄷ ㄷㄷ ㄷㄷ ㄷㄷ.jpg",
    "url": "https://www.ppomppu.co.kr/zboard/view.php?id=freeboard&page=1&divpage=1855&no=9934992",
    "thumb": null,
    "score": 0,
    "views": null,
    "crawled_at": "2026-05-11T22:49:23.782562+00:00"
  },
  {
    "id": "9934990",
    "site": "ppomppu",
    "title": "신임 검사, 지방 로스쿨 60% 육박(기사)",
    "url": "https://www.ppomppu.co.kr/zboard/view.php?id=freeboard&page=1&divpage=1855&no=9934990",
    "thumb": null,
    "score": 0,
    "views": null,
    "crawled_at": "2026-05-11T22:49:23.782562+00:00"
  },
  {
    "id": "9934989",
    "site": "ppomppu",
    "title": "단독]최태원 동거인 2000만원 손해배상 받는다..",
    "url": "https://www.ppomppu.co.kr/zboard/view.php?id=freeboard&page=1&divpage=1855&no=9934989",
    "thumb": null,
    "score": 0,
    "views": null,
    "crawled_at": "2026-05-11T22:49:23.782562+00:00"
  },
  {
    "id": "9934988",
    "site": "ppomppu",
    "title": "주식 투자 조언하는 증권 센터장",
    "url": "https://www.ppomppu.co.kr/zboard/view.php?id=freeboard&page=1&divpage=1855&no=9934988",
    "thumb": null,
    "score": 0,
    "views": null,
    "crawled_at": "2026-05-11T22:49:23.782562+00:00"
  },
  {
    "id": "9934986",
    "site": "ppomppu",
    "title": "앞으로 응급실에서 의사 찾기 힘들겠다",
    "url": "https://www.ppomppu.co.kr/zboard/view.php?id=freeboard&page=1&divpage=1855&no=9934986",
    "thumb": null,
    "score": 0,
    "views": null,
    "crawled_at": "2026-05-11T22:49:23.782562+00:00"
  },
  {
    "id": "9934985",
    "site": "ppomppu",
    "title": "삼성전자에대한 일본인들의 반응",
    "url": "https://www.ppomppu.co.kr/zboard/view.php?id=freeboard&page=1&divpage=1855&no=9934985",
    "thumb": null,
    "score": 0,
    "views": null,
    "crawled_at": "2026-05-11T22:49:23.782562+00:00"
  }
]