[
  {
    "id": "4280913452",
    "site": "theqoo",
    "title": "[단독]도경수, ‘위아더좀비’로 안방 복귀…이번엔 좀비물 도전",
    "url": "https://theqoo.net/square/4280913452",
    "thumb": null,
    "score": 10006,
    "views": null,
    "crawled_at": "2026-07-15T22:53:35.977633+00:00"
  },
  {
    "id": "4280920541",
    "site": "theqoo",
    "title": "CT 찍으시는 ‘세계 3위’ 국중박 불좌상",
    "url": "https://theqoo.net/square/4280920541",
    "thumb": null,
    "score": 5672,
    "views": null,
    "crawled_at": "2026-07-15T22:53:35.977633+00:00"
  },
  {
    "id": "4280918182",
    "site": "theqoo",
    "title": "과학자들 멘탈 털어버리는 박성준 역술가의 말빨 클래스 ㅋㅋㅋㅋㅋㅋ",
    "url": "https://theqoo.net/square/4280918182",
    "thumb": null,
    "score": 4100,
    "views": null,
    "crawled_at": "2026-07-15T22:53:35.977633+00:00"
  },
  {
    "id": "4280931553",
    "site": "theqoo",
    "title": "생활고 이유로 딸 살해 후 자살하려던 부부, 선처받은 이유",
    "url": "https://theqoo.net/square/4280931553",
    "thumb": null,
    "score": 3209,
    "views": null,
    "crawled_at": "2026-07-15T22:53:35.977633+00:00"
  },
  {
    "id": "4280932863",
    "site": "theqoo",
    "title": "빗길에서 아이를 출산한 중국 BYD 자동차",
    "url": "https://theqoo.net/square/4280932863",
    "thumb": null,
    "score": 2335,
    "views": null,
    "crawled_at": "2026-07-15T22:53:35.977633+00:00"
  },
  {
    "id": "4280933293",
    "site": "theqoo",
    "title": "아르헨티나가 이기며 결승에서 맞붙게 된 메시와 야말",
    "url": "https://theqoo.net/square/4280933293",
    "thumb": null,
    "score": 2156,
    "views": null,
    "crawled_at": "2026-07-15T22:53:35.977633+00:00"
  },
  {
    "id": "4280935952",
    "site": "theqoo",
    "title": "2026년 미국에서 상반기에 가장많이 팔린 K-Pop CD 앨범 순위",
    "url": "https://theqoo.net/square/4280935952",
    "thumb": null,
    "score": 1407,
    "views": null,
    "crawled_at": "2026-07-15T22:53:35.977633+00:00"
  },
  {
    "id": "4280923481",
    "site": "theqoo",
    "title": "사육사와 모자로 장난치는 코끼리 🐘🧢(우리가 잘 아는 그 유명한 짤 아님)",
    "url": "https://theqoo.net/square/4280923481",
    "thumb": null,
    "score": 1122,
    "views": null,
    "crawled_at": "2026-07-15T22:53:35.977633+00:00"
  },
  {
    "id": "4280915852",
    "site": "theqoo",
    "title": "요즘같이더운날에는",
    "url": "https://theqoo.net/square/4280915852",
    "thumb": null,
    "score": 821,
    "views": null,
    "crawled_at": "2026-07-15T22:53:35.977633+00:00"
  },
  {
    "id": "4280930018",
    "site": "theqoo",
    "title": "루이바오에게 궁금한 거 🤔 본판도 투턱판다라 생각할지 🩷",
    "url": "https://theqoo.net/square/4280930018",
    "thumb": null,
    "score": 719,
    "views": null,
    "crawled_at": "2026-07-15T22:53:35.977633+00:00"
  },
  {
    "id": "4280933093",
    "site": "theqoo",
    "title": "득도한 고양이",
    "url": "https://theqoo.net/square/4280933093",
    "thumb": null,
    "score": 666,
    "views": null,
    "crawled_at": "2026-07-15T22:53:35.977633+00:00"
  },
  {
    "id": "4280928179",
    "site": "theqoo",
    "title": "5년전 2pm 준호",
    "url": "https://theqoo.net/square/4280928179",
    "thumb": null,
    "score": 550,
    "views": null,
    "crawled_at": "2026-07-15T22:53:35.977633+00:00"
  },
  {
    "id": "4280939954",
    "site": "theqoo",
    "title": "이번 월드컵 결승 진출한 2개국이랑 90분 무승부 기록한 유일한 나라 카보베르데",
    "url": "https://theqoo.net/square/4280939954",
    "thumb": null,
    "score": 329,
    "views": null,
    "crawled_at": "2026-07-15T22:53:35.977633+00:00"
  },
  {
    "id": "4280926473",
    "site": "theqoo",
    "title": "연기·노래 잡은 박지훈, 9월 亞 팬콘 앙코르 콘서트 개최 [공식]",
    "url": "https://theqoo.net/square/4280926473",
    "thumb": null,
    "score": 323,
    "views": null,
    "crawled_at": "2026-07-15T22:53:35.977633+00:00"
  },
  {
    "id": "4280939688",
    "site": "theqoo",
    "title": "마이크 리 감독 <내 말 좀 들어줘> 넷플릭스에 올라옴",
    "url": "https://theqoo.net/square/4280939688",
    "thumb": null,
    "score": 245,
    "views": null,
    "crawled_at": "2026-07-15T22:53:35.977633+00:00"
  },
  {
    "id": "4280931455",
    "site": "theqoo",
    "title": "믿.보.배 몰려온다… 박은빈·공효진·김혜수, 7월 안방극장 '출격'",
    "url": "https://theqoo.net/square/4280931455",
    "thumb": null,
    "score": 216,
    "views": null,
    "crawled_at": "2026-07-15T22:53:35.977633+00:00"
  },
  {
    "id": "300143",
    "site": "ruliweb",
    "title": "야쿠자 영화를 보는데, 어쩐지 정답다.jpg",
    "url": "https://bbs.ruliweb.com/community/board/300143/read/75959500?",
    "thumb": null,
    "score": 3,
    "views": 125,
    "crawled_at": "2026-07-15T22:53:35.977633+00:00"
  },
  {
    "id": "300143",
    "site": "ruliweb",
    "title": "메이드의 성교육 시간 만화",
    "url": "https://bbs.ruliweb.com/community/board/300143/read/75959512?",
    "thumb": null,
    "score": 2,
    "views": 54,
    "crawled_at": "2026-07-15T22:53:35.977633+00:00"
  },
  {
    "id": "300143",
    "site": "ruliweb",
    "title": "말딸) 디지땅의 승부복을 입은 오르페브르(2)",
    "url": "https://bbs.ruliweb.com/community/board/300143/read/75959511?",
    "thumb": null,
    "score": 2,
    "views": 48,
    "crawled_at": "2026-07-15T22:53:35.977633+00:00"
  },
  {
    "id": "300143",
    "site": "ruliweb",
    "title": "야 겁대가리없이 설치는 유게빌런 놈들한테 경고한다(2)",
    "url": "https://bbs.ruliweb.com/community/board/300143/read/75959506?",
    "thumb": null,
    "score": 2,
    "views": 55,
    "crawled_at": "2026-07-15T22:53:35.977633+00:00"
  },
  {
    "id": "300143",
    "site": "ruliweb",
    "title": "교외로 데이트 나온 비둘기 커플.mp4",
    "url": "https://bbs.ruliweb.com/community/board/300143/read/75959514?",
    "thumb": null,
    "score": 1,
    "views": 36,
    "crawled_at": "2026-07-15T22:53:35.977633+00:00"
  },
  {
    "id": "300143",
    "site": "ruliweb",
    "title": "아니 님들 님들만 새벽에 재밌는 거 보면 어떻게 해요(1)",
    "url": "https://bbs.ruliweb.com/community/board/300143/read/75959513?",
    "thumb": null,
    "score": 1,
    "views": 42,
    "crawled_at": "2026-07-15T22:53:35.977633+00:00"
  },
  {
    "id": "300143",
    "site": "ruliweb",
    "title": "바키) 2부 사형수에 관해 오해하는게(1)",
    "url": "https://bbs.ruliweb.com/community/board/300143/read/75959509?",
    "thumb": null,
    "score": 1,
    "views": 31,
    "crawled_at": "2026-07-15T22:53:35.977633+00:00"
  },
  {
    "id": "300143",
    "site": "ruliweb",
    "title": "프랑스 새끼들 아주 편한가봄(1)",
    "url": "https://bbs.ruliweb.com/community/board/300143/read/75959507?",
    "thumb": null,
    "score": 1,
    "views": 122,
    "crawled_at": "2026-07-15T22:53:35.977633+00:00"
  },
  {
    "id": "300143",
    "site": "ruliweb",
    "title": "주식)오늘도 흘러내리겠네(1)",
    "url": "https://bbs.ruliweb.com/community/board/300143/read/75959505?",
    "thumb": null,
    "score": 1,
    "views": 70,
    "crawled_at": "2026-07-15T22:53:35.977633+00:00"
  },
  {
    "id": "300143",
    "site": "ruliweb",
    "title": "아티스트의 악상이 떠오른 순간",
    "url": "https://bbs.ruliweb.com/community/board/300143/read/75959504?",
    "thumb": null,
    "score": 1,
    "views": 37,
    "crawled_at": "2026-07-15T22:53:35.977633+00:00"
  },
  {
    "id": "10039580",
    "site": "ppomppu",
    "title": "아파트 세대내 흡연충은 답이 없네요.",
    "url": "https://www.ppomppu.co.kr/zboard/view.php?id=freeboard&page=1&divpage=1875&no=10039580",
    "thumb": null,
    "score": 1,
    "views": null,
    "crawled_at": "2026-07-15T22:53:35.977633+00:00"
  },
  {
    "id": "10039575",
    "site": "ppomppu",
    "title": "검찰개혁은 빠르게 완벽하게 박살래라",
    "url": "https://www.ppomppu.co.kr/zboard/view.php?id=freeboard&page=1&divpage=1875&no=10039575",
    "thumb": null,
    "score": 1,
    "views": null,
    "crawled_at": "2026-07-15T22:53:35.977633+00:00"
  },
  {
    "id": "10039571",
    "site": "ppomppu",
    "title": "요즈음 2030은 먹어본 적 없다는 호프가게 안주 jpg",
    "url": "https://www.ppomppu.co.kr/zboard/view.php?id=freeboard&page=1&divpage=1875&no=10039571",
    "thumb": null,
    "score": 1,
    "views": null,
    "crawled_at": "2026-07-15T22:53:35.977633+00:00"
  },
  {
    "id": "10039569",
    "site": "ppomppu",
    "title": "그런데 이번에 티빙 사태는 왜이리 조용한 걸까요?",
    "url": "https://www.ppomppu.co.kr/zboard/view.php?id=freeboard&page=1&divpage=1875&no=10039569",
    "thumb": null,
    "score": 1,
    "views": null,
    "crawled_at": "2026-07-15T22:53:35.977633+00:00"
  },
  {
    "id": "10039568",
    "site": "ppomppu",
    "title": "태풍 바비가 만들어낸 한반도의 열돔변화",
    "url": "https://www.ppomppu.co.kr/zboard/view.php?id=freeboard&page=1&divpage=1875&no=10039568",
    "thumb": null,
    "score": 1,
    "views": null,
    "crawled_at": "2026-07-15T22:53:35.977633+00:00"
  },
  {
    "id": "10039566",
    "site": "ppomppu",
    "title": "성수대교 9cm 단차 지점에 \"부러진 척추\" 엑스레이 광고",
    "url": "https://www.ppomppu.co.kr/zboard/view.php?id=freeboard&page=1&divpage=1875&no=10039566",
    "thumb": null,
    "score": 1,
    "views": null,
    "crawled_at": "2026-07-15T22:53:35.977633+00:00"
  },
  {
    "id": "10039563",
    "site": "ppomppu",
    "title": "유시민 나는 이재명 선거운동원도 자원봉사자도 아니야",
    "url": "https://www.ppomppu.co.kr/zboard/view.php?id=freeboard&page=1&divpage=1875&no=10039563",
    "thumb": null,
    "score": 1,
    "views": null,
    "crawled_at": "2026-07-15T22:53:35.977633+00:00"
  },
  {
    "id": "300142",
    "site": "ruliweb",
    "title": "엔비다아 쉐이더 캐시 사이즈 질문",
    "url": "https://bbs.ruliweb.com/community/board/300142/read/30619702",
    "thumb": null,
    "score": 0,
    "views": 637,
    "crawled_at": "2026-07-15T22:53:35.977633+00:00"
  },
  {
    "id": "110135",
    "site": "ruliweb",
    "title": "선수 소개 삭제인가요?",
    "url": "https://bbs.ruliweb.com/etcs/board/110135/read/9415321",
    "thumb": null,
    "score": 0,
    "views": 713,
    "crawled_at": "2026-07-15T22:53:35.977633+00:00"
  },
  {
    "id": "300059",
    "site": "ruliweb",
    "title": "모바일 게임 (방구석선물왕)",
    "url": "https://bbs.ruliweb.com/etcs/board/300059/read/30573185",
    "thumb": null,
    "score": 0,
    "views": 88,
    "crawled_at": "2026-07-15T22:53:35.977633+00:00"
  },
  {
    "id": "300143",
    "site": "ruliweb",
    "title": "결착땽뭐임",
    "url": "https://bbs.ruliweb.com/community/board/300143/read/75959516?",
    "thumb": null,
    "score": 0,
    "views": 7,
    "crawled_at": "2026-07-15T22:53:35.977633+00:00"
  },
  {
    "id": "300143",
    "site": "ruliweb",
    "title": "한요일) 오늘자 개맛있네",
    "url": "https://bbs.ruliweb.com/community/board/300143/read/75959515?",
    "thumb": null,
    "score": 0,
    "views": 7,
    "crawled_at": "2026-07-15T22:53:35.977633+00:00"
  },
  {
    "id": "300143",
    "site": "ruliweb",
    "title": "가끔 이게 주식하는 기분인가 함",
    "url": "https://bbs.ruliweb.com/community/board/300143/read/75959510?",
    "thumb": null,
    "score": 0,
    "views": 81,
    "crawled_at": "2026-07-15T22:53:35.977633+00:00"
  },
  {
    "id": "300143",
    "site": "ruliweb",
    "title": "전동칫솔 사야하는데 브랜드를 바꿔볼까?",
    "url": "https://bbs.ruliweb.com/community/board/300143/read/75959508?",
    "thumb": null,
    "score": 0,
    "views": 20,
    "crawled_at": "2026-07-15T22:53:35.977633+00:00"
  },
  {
    "id": "300143",
    "site": "ruliweb",
    "title": "스페인한테 진 프랑스 근황(6)",
    "url": "https://bbs.ruliweb.com/community/board/300143/read/75959503?",
    "thumb": null,
    "score": 0,
    "views": 106,
    "crawled_at": "2026-07-15T22:53:35.977633+00:00"
  },
  {
    "id": "300143",
    "site": "ruliweb",
    "title": "월드컵) 자다가 더워서 깼는데 아르헨티나가 이겼네??",
    "url": "https://bbs.ruliweb.com/community/board/300143/read/75959502?",
    "thumb": null,
    "score": 0,
    "views": 66,
    "crawled_at": "2026-07-15T22:53:35.977633+00:00"
  },
  {
    "id": "300143",
    "site": "ruliweb",
    "title": "브더2) 코스로 불타는 거 이해는 되네",
    "url": "https://bbs.ruliweb.com/community/board/300143/read/75959501?",
    "thumb": null,
    "score": 0,
    "views": 100,
    "crawled_at": "2026-07-15T22:53:35.977633+00:00"
  },
  {
    "id": "3836786021",
    "site": "theqoo",
    "title": "[스퀘어게시판 정치 카테고리 추가 및 정치 제외 기능 추가]",
    "url": "https://theqoo.net/square/3836786021",
    "thumb": null,
    "score": 0,
    "views": null,
    "crawled_at": "2026-07-15T22:53:35.977633+00:00"
  },
  {
    "id": "1638396273",
    "site": "theqoo",
    "title": "나는 더쿠에서 움짤을 한 번이라도 올려본 적이 있다 🙋‍♀️",
    "url": "https://theqoo.net/square/1638396273",
    "thumb": null,
    "score": 0,
    "views": null,
    "crawled_at": "2026-07-15T22:53:35.977633+00:00"
  },
  {
    "id": "1419228502",
    "site": "theqoo",
    "title": "더쿠에 쉽게 동영상을 올려보자 !",
    "url": "https://theqoo.net/square/1419228502",
    "thumb": null,
    "score": 0,
    "views": null,
    "crawled_at": "2026-07-15T22:53:35.977633+00:00"
  },
  {
    "id": "1386342829",
    "site": "theqoo",
    "title": "슬기로운 더쿠생활 : 더쿠 이용팁",
    "url": "https://theqoo.net/square/1386342829",
    "thumb": null,
    "score": 0,
    "views": null,
    "crawled_at": "2026-07-15T22:53:35.977633+00:00"
  },
  {
    "id": "10039581",
    "site": "ppomppu",
    "title": "오늘은 운이 좋네요ㅋㅋ",
    "url": "https://www.ppomppu.co.kr/zboard/view.php?id=freeboard&page=1&divpage=1875&no=10039581",
    "thumb": null,
    "score": 0,
    "views": null,
    "crawled_at": "2026-07-15T22:53:35.977633+00:00"
  },
  {
    "id": "10039579",
    "site": "ppomppu",
    "title": "\"완벽한 왕위 계승식\" 야말의 스페인, 메시의 아르헨 누르고 우승",
    "url": "https://www.ppomppu.co.kr/zboard/view.php?id=freeboard&page=1&divpage=1875&no=10039579",
    "thumb": null,
    "score": 0,
    "views": null,
    "crawled_at": "2026-07-15T22:53:35.977633+00:00"
  },
  {
    "id": "10039578",
    "site": "ppomppu",
    "title": "CBDC 안했으면좋겠음",
    "url": "https://www.ppomppu.co.kr/zboard/view.php?id=freeboard&page=1&divpage=1875&no=10039578",
    "thumb": null,
    "score": 0,
    "views": null,
    "crawled_at": "2026-07-15T22:53:35.977633+00:00"
  },
  {
    "id": "10039577",
    "site": "ppomppu",
    "title": "자수하러 경찰서 갔더니..갑자기 밖으로 불러내 긴급체포한 경찰관",
    "url": "https://www.ppomppu.co.kr/zboard/view.php?id=freeboard&page=1&divpage=1875&no=10039577",
    "thumb": null,
    "score": 0,
    "views": null,
    "crawled_at": "2026-07-15T22:53:35.977633+00:00"
  },
  {
    "id": "10039576",
    "site": "ppomppu",
    "title": "스페인이 보여주는 후방 빌드업의 예시",
    "url": "https://www.ppomppu.co.kr/zboard/view.php?id=freeboard&page=1&divpage=1875&no=10039576",
    "thumb": null,
    "score": 0,
    "views": null,
    "crawled_at": "2026-07-15T22:53:35.977633+00:00"
  },
  {
    "id": "10039574",
    "site": "ppomppu",
    "title": "스페인 vs 아르헨",
    "url": "https://www.ppomppu.co.kr/zboard/view.php?id=freeboard&page=1&divpage=1875&no=10039574",
    "thumb": null,
    "score": 0,
    "views": null,
    "crawled_at": "2026-07-15T22:53:35.977633+00:00"
  },
  {
    "id": "10039573",
    "site": "ppomppu",
    "title": "갑자기 정권에 가까워진 사람들 대통령이 아니라 비서실장 전화만 받아도 도파민 ...",
    "url": "https://www.ppomppu.co.kr/zboard/view.php?id=freeboard&page=1&divpage=1875&no=10039573",
    "thumb": null,
    "score": 0,
    "views": null,
    "crawled_at": "2026-07-15T22:53:35.977633+00:00"
  },
  {
    "id": "10039572",
    "site": "ppomppu",
    "title": "장외 맴돌며 '극우 선동'. \"거기서 뭐 하나\"",
    "url": "https://www.ppomppu.co.kr/zboard/view.php?id=freeboard&page=1&divpage=1875&no=10039572",
    "thumb": null,
    "score": 0,
    "views": null,
    "crawled_at": "2026-07-15T22:53:35.977633+00:00"
  },
  {
    "id": "10039570",
    "site": "ppomppu",
    "title": "투헬감독 그래서 명장입니까??",
    "url": "https://www.ppomppu.co.kr/zboard/view.php?id=freeboard&page=1&divpage=1875&no=10039570",
    "thumb": null,
    "score": 0,
    "views": null,
    "crawled_at": "2026-07-15T22:53:35.977633+00:00"
  },
  {
    "id": "10039567",
    "site": "ppomppu",
    "title": "메시는 은퇴하고 축구감독할까요",
    "url": "https://www.ppomppu.co.kr/zboard/view.php?id=freeboard&page=1&divpage=1875&no=10039567",
    "thumb": null,
    "score": 0,
    "views": null,
    "crawled_at": "2026-07-15T22:53:35.977633+00:00"
  },
  {
    "id": "10039565",
    "site": "ppomppu",
    "title": "아르헨티나 출산율 폭증하겠네요",
    "url": "https://www.ppomppu.co.kr/zboard/view.php?id=freeboard&page=1&divpage=1875&no=10039565",
    "thumb": null,
    "score": 0,
    "views": null,
    "crawled_at": "2026-07-15T22:53:35.977633+00:00"
  },
  {
    "id": "10039564",
    "site": "ppomppu",
    "title": "임기 4년이나 남았는데 이러면 지지자들 어쩌라는겨",
    "url": "https://www.ppomppu.co.kr/zboard/view.php?id=freeboard&page=1&divpage=1875&no=10039564",
    "thumb": null,
    "score": 0,
    "views": null,
    "crawled_at": "2026-07-15T22:53:35.977633+00:00"
  },
  {
    "id": "10039562",
    "site": "ppomppu",
    "title": "결승전 말고 3,4위전도 개꿀잼매치",
    "url": "https://www.ppomppu.co.kr/zboard/view.php?id=freeboard&page=1&divpage=1875&no=10039562",
    "thumb": null,
    "score": 0,
    "views": null,
    "crawled_at": "2026-07-15T22:53:35.977633+00:00"
  }
]