[
  {
    "id": "4230028060",
    "site": "theqoo",
    "title": "최성곤 니가 좋아 반응에 신난 듯한 오정세 소속사ㅋㅋㅋㅋ",
    "url": "https://theqoo.net/square/4230028060",
    "thumb": null,
    "score": 2762,
    "views": null,
    "crawled_at": "2026-06-04T03:28:52.609300+00:00"
  },
  {
    "id": "4230028385",
    "site": "theqoo",
    "title": "김민석 떠나면 총리는 누구…강훈식·정성호·한성숙 거론",
    "url": "https://theqoo.net/square/4230028385",
    "thumb": null,
    "score": 1451,
    "views": null,
    "crawled_at": "2026-06-04T03:28:52.609300+00:00"
  },
  {
    "id": "4230031131",
    "site": "theqoo",
    "title": "이승기 \"전세금 3배 요구해 105억\"…차가원 측 \"이승기가 착각\"[종합]",
    "url": "https://theqoo.net/square/4230031131",
    "thumb": null,
    "score": 1313,
    "views": null,
    "crawled_at": "2026-06-04T03:28:52.609300+00:00"
  },
  {
    "id": "4230038870",
    "site": "theqoo",
    "title": "피의게임 서울대출신 의사 신승용 참가.jpg",
    "url": "https://theqoo.net/square/4230038870",
    "thumb": null,
    "score": 898,
    "views": null,
    "crawled_at": "2026-06-04T03:28:52.609300+00:00"
  },
  {
    "id": "4230027730",
    "site": "theqoo",
    "title": "단콘인 줄 알았다는 3세대 아이돌 음방 무대",
    "url": "https://theqoo.net/square/4230027730",
    "thumb": null,
    "score": 652,
    "views": null,
    "crawled_at": "2026-06-04T03:28:52.609300+00:00"
  },
  {
    "id": "4230040795",
    "site": "theqoo",
    "title": "방송에서 새끼사자가 아기를 물려고 한 사건 in 멕시코",
    "url": "https://theqoo.net/square/4230040795",
    "thumb": null,
    "score": 504,
    "views": null,
    "crawled_at": "2026-06-04T03:28:52.609300+00:00"
  },
  {
    "id": "4230034289",
    "site": "theqoo",
    "title": "빽가 “JYP 안무팀 시절, 윗 사람이 차키 던져…데뷔 후 태세 전환”(라디오쇼)",
    "url": "https://theqoo.net/square/4230034289",
    "thumb": null,
    "score": 494,
    "views": null,
    "crawled_at": "2026-06-04T03:28:52.609300+00:00"
  },
  {
    "id": "4230037863",
    "site": "theqoo",
    "title": "채널십오야, 中 자막 논란에 사과…\"왜 스레드에만?\" 대만 팬들 싸늘 [ST이슈]",
    "url": "https://theqoo.net/square/4230037863",
    "thumb": null,
    "score": 458,
    "views": null,
    "crawled_at": "2026-06-04T03:28:52.609300+00:00"
  },
  {
    "id": "4230037371",
    "site": "theqoo",
    "title": "난쏘공을 쓴 조세희 선생님이 생전에 했던 말을 종종 떠올리곤 함. 냉소하지 말라고. 냉소주의는 사람의 기운을 빼앗아간다고. 절대 희망을 놓지 말라고. 곱씹어보면 이 말이 되게 위로가 될 때가 많음.",
    "url": "https://theqoo.net/square/4230037371",
    "thumb": null,
    "score": 311,
    "views": null,
    "crawled_at": "2026-06-04T03:28:52.609300+00:00"
  },
  {
    "id": "4230044637",
    "site": "theqoo",
    "title": "오세훈은 전국을 구하기 위해 서울을 망치러 온 구원자",
    "url": "https://theqoo.net/square/4230044637",
    "thumb": null,
    "score": 268,
    "views": null,
    "crawled_at": "2026-06-04T03:28:52.609300+00:00"
  },
  {
    "id": "4230044069",
    "site": "theqoo",
    "title": "쉬었음ㅇㅇㅇ",
    "url": "https://theqoo.net/square/4230044069",
    "thumb": null,
    "score": 255,
    "views": null,
    "crawled_at": "2026-06-04T03:28:52.609300+00:00"
  },
  {
    "id": "4230039733",
    "site": "theqoo",
    "title": "인스타로 축구 입중계하는 윤두준ㅋㅋㅋㅋㅋㅋㅋㅋㅋㅋㅋㅋㅋ",
    "url": "https://theqoo.net/square/4230039733",
    "thumb": null,
    "score": 246,
    "views": null,
    "crawled_at": "2026-06-04T03:28:52.609300+00:00"
  },
  {
    "id": "4230041269",
    "site": "theqoo",
    "title": "[단독] \"장기전세 분양\" vs \"혜택 끝, 떠나야\" 논쟁 격화… 내 집 마련은 7%뿐",
    "url": "https://theqoo.net/square/4230041269",
    "thumb": null,
    "score": 179,
    "views": null,
    "crawled_at": "2026-06-04T03:28:52.609300+00:00"
  },
  {
    "id": "4230045048",
    "site": "theqoo",
    "title": "AI 이전, 우리는 이 사람을 갖고있었다",
    "url": "https://theqoo.net/square/4230045048",
    "thumb": null,
    "score": 140,
    "views": null,
    "crawled_at": "2026-06-04T03:28:52.609300+00:00"
  },
  {
    "id": "4230035789",
    "site": "theqoo",
    "title": "마마무, 오늘 완전체 컴백…3년 8개월만",
    "url": "https://theqoo.net/square/4230035789",
    "thumb": null,
    "score": 91,
    "views": null,
    "crawled_at": "2026-06-04T03:28:52.609300+00:00"
  },
  {
    "id": "4230035145",
    "site": "theqoo",
    "title": "MEOVV - ‘띠로리 (DDI RO RI)’ 응원법",
    "url": "https://theqoo.net/square/4230035145",
    "thumb": null,
    "score": 45,
    "views": null,
    "crawled_at": "2026-06-04T03:28:52.609300+00:00"
  },
  {
    "id": "9966410",
    "site": "ppomppu",
    "title": "일단 대구신공항 백지화부터",
    "url": "https://www.ppomppu.co.kr/zboard/view.php?id=freeboard&page=1&divpage=1861&no=9966410",
    "thumb": null,
    "score": 7,
    "views": null,
    "crawled_at": "2026-06-04T03:28:52.609300+00:00"
  },
  {
    "id": "9966411",
    "site": "ppomppu",
    "title": "Jtbc)김민석 사의표명 관측",
    "url": "https://www.ppomppu.co.kr/zboard/view.php?id=freeboard&page=1&divpage=1861&no=9966411",
    "thumb": null,
    "score": 4,
    "views": null,
    "crawled_at": "2026-06-04T03:28:52.609300+00:00"
  },
  {
    "id": "9966407",
    "site": "ppomppu",
    "title": "군대 다시 24개월 월급 다시 18만원으로 돌리면 어때요?",
    "url": "https://www.ppomppu.co.kr/zboard/view.php?id=freeboard&page=1&divpage=1861&no=9966407",
    "thumb": null,
    "score": 4,
    "views": null,
    "crawled_at": "2026-06-04T03:28:52.609300+00:00"
  },
  {
    "id": "300142",
    "site": "ruliweb",
    "title": "플스5 관련인대요 이게 고장인거 같은대",
    "url": "https://bbs.ruliweb.com/community/board/300142/read/30619502",
    "thumb": null,
    "score": 3,
    "views": 557,
    "crawled_at": "2026-06-04T03:28:52.609300+00:00"
  },
  {
    "id": "300143",
    "site": "ruliweb",
    "title": "꺼무위키에서 캐릭터 평가 항목은 재미로 봐야하는 이유",
    "url": "https://bbs.ruliweb.com/community/board/300143/read/75435221?",
    "thumb": null,
    "score": 3,
    "views": 60,
    "crawled_at": "2026-06-04T03:28:52.609300+00:00"
  },
  {
    "id": "300143",
    "site": "ruliweb",
    "title": "블루아카) 왜 슬렌더 가지고 싸우냐 슬렌더만큼 좋은게 어디있다고(1)",
    "url": "https://bbs.ruliweb.com/community/board/300143/read/75435223?",
    "thumb": null,
    "score": 2,
    "views": 43,
    "crawled_at": "2026-06-04T03:28:52.609300+00:00"
  },
  {
    "id": "300143",
    "site": "ruliweb",
    "title": "대부분이 몰랐을 블러드본 속 이스터에그.jpg(2)",
    "url": "https://bbs.ruliweb.com/community/board/300143/read/75435220?",
    "thumb": null,
    "score": 2,
    "views": 70,
    "crawled_at": "2026-06-04T03:28:52.609300+00:00"
  },
  {
    "id": "300143",
    "site": "ruliweb",
    "title": "니케) 음침 서큐버스 레이블💜(2)",
    "url": "https://bbs.ruliweb.com/community/board/300143/read/75435218?",
    "thumb": null,
    "score": 2,
    "views": 49,
    "crawled_at": "2026-06-04T03:28:52.609300+00:00"
  },
  {
    "id": "300143",
    "site": "ruliweb",
    "title": "인형탈 도로롱(2)",
    "url": "https://bbs.ruliweb.com/community/board/300143/read/75435216?",
    "thumb": null,
    "score": 2,
    "views": 64,
    "crawled_at": "2026-06-04T03:28:52.609300+00:00"
  },
  {
    "id": "300143",
    "site": "ruliweb",
    "title": "애낳을 생각 없다고 돌려말하는 법.jpg(1)",
    "url": "https://bbs.ruliweb.com/community/board/300143/read/75435222?",
    "thumb": null,
    "score": 1,
    "views": 102,
    "crawled_at": "2026-06-04T03:28:52.609300+00:00"
  },
  {
    "id": "300143",
    "site": "ruliweb",
    "title": "스타크래프트 로템에서 1시간넘게 햇네(2)",
    "url": "https://bbs.ruliweb.com/community/board/300143/read/75435219?",
    "thumb": null,
    "score": 1,
    "views": 51,
    "crawled_at": "2026-06-04T03:28:52.609300+00:00"
  },
  {
    "id": "300143",
    "site": "ruliweb",
    "title": "버거킨 롱치킹 부활(1)",
    "url": "https://bbs.ruliweb.com/community/board/300143/read/75435217?",
    "thumb": null,
    "score": 1,
    "views": 75,
    "crawled_at": "2026-06-04T03:28:52.609300+00:00"
  },
  {
    "id": "9966416",
    "site": "ppomppu",
    "title": "서울시장은 여조상으로도 접전이였습니다.",
    "url": "https://www.ppomppu.co.kr/zboard/view.php?id=freeboard&page=1&divpage=1861&no=9966416",
    "thumb": null,
    "score": 1,
    "views": null,
    "crawled_at": "2026-06-04T03:28:52.609300+00:00"
  },
  {
    "id": "9966404",
    "site": "ppomppu",
    "title": "25년 헌재 \"선관위는 감사원 감사 대상 아니다..독립업무 수행 침해\"",
    "url": "https://www.ppomppu.co.kr/zboard/view.php?id=freeboard&page=1&divpage=1861&no=9966404",
    "thumb": null,
    "score": 1,
    "views": null,
    "crawled_at": "2026-06-04T03:28:52.609300+00:00"
  },
  {
    "id": "9966400",
    "site": "ppomppu",
    "title": "현재 달러 환율 집중..",
    "url": "https://www.ppomppu.co.kr/zboard/view.php?id=freeboard&page=1&divpage=1861&no=9966400",
    "thumb": null,
    "score": 1,
    "views": null,
    "crawled_at": "2026-06-04T03:28:52.609300+00:00"
  },
  {
    "id": "300118",
    "site": "ruliweb",
    "title": "76323 혹시 오프라인 재고 있나요?",
    "url": "https://bbs.ruliweb.com/etcs/board/300118/read/30568496",
    "thumb": null,
    "score": 0,
    "views": 138,
    "crawled_at": "2026-06-04T03:28:52.609300+00:00"
  },
  {
    "id": "184111",
    "site": "ruliweb",
    "title": "fl26 컵모드 하는데 골 직전에 프리징 현상 고치는법 아시는 능력자분?",
    "url": "https://bbs.ruliweb.com/etcs/board/184111/read/217049",
    "thumb": null,
    "score": 0,
    "views": 99,
    "crawled_at": "2026-06-04T03:28:52.609300+00:00"
  },
  {
    "id": "300143",
    "site": "ruliweb",
    "title": "워해머) 황제폐하가 옥좌에서 벌떡 일어날 장면",
    "url": "https://bbs.ruliweb.com/community/board/300143/read/75435232?",
    "thumb": null,
    "score": 0,
    "views": 1,
    "crawled_at": "2026-06-04T03:28:52.609300+00:00"
  },
  {
    "id": "300143",
    "site": "ruliweb",
    "title": "아내가 일본여자긴한데 잘지내고 있음",
    "url": "https://bbs.ruliweb.com/community/board/300143/read/75435231?",
    "thumb": null,
    "score": 0,
    "views": 1,
    "crawled_at": "2026-06-04T03:28:52.609300+00:00"
  },
  {
    "id": "300143",
    "site": "ruliweb",
    "title": "안전보다 간식에 최적화된 핸들",
    "url": "https://bbs.ruliweb.com/community/board/300143/read/75435230?",
    "thumb": null,
    "score": 0,
    "views": 6,
    "crawled_at": "2026-06-04T03:28:52.609300+00:00"
  },
  {
    "id": "300143",
    "site": "ruliweb",
    "title": "555 달성",
    "url": "https://bbs.ruliweb.com/community/board/300143/read/75435229?",
    "thumb": null,
    "score": 0,
    "views": 12,
    "crawled_at": "2026-06-04T03:28:52.609300+00:00"
  },
  {
    "id": "300143",
    "site": "ruliweb",
    "title": "흡혈귀 여고생이 선생을 협박하는 만화",
    "url": "https://bbs.ruliweb.com/community/board/300143/read/75435228?",
    "thumb": null,
    "score": 0,
    "views": 27,
    "crawled_at": "2026-06-04T03:28:52.609300+00:00"
  },
  {
    "id": "300143",
    "site": "ruliweb",
    "title": "오늘 내 치지직 방송에서 할 게임들(1)",
    "url": "https://bbs.ruliweb.com/community/board/300143/read/75435227?",
    "thumb": null,
    "score": 0,
    "views": 39,
    "crawled_at": "2026-06-04T03:28:52.609300+00:00"
  },
  {
    "id": "300143",
    "site": "ruliweb",
    "title": "마운자로 맞아서 배는 안고픈데 점심 먹어야하나",
    "url": "https://bbs.ruliweb.com/community/board/300143/read/75435226?",
    "thumb": null,
    "score": 0,
    "views": 11,
    "crawled_at": "2026-06-04T03:28:52.609300+00:00"
  },
  {
    "id": "300143",
    "site": "ruliweb",
    "title": "남자라도 가능한게 아니라 이 아마추어 뉴비 유게이쉨들아",
    "url": "https://bbs.ruliweb.com/community/board/300143/read/75435225?",
    "thumb": null,
    "score": 0,
    "views": 18,
    "crawled_at": "2026-06-04T03:28:52.609300+00:00"
  },
  {
    "id": "300143",
    "site": "ruliweb",
    "title": "내 마누라면 20분정도 쉬러 간다.(2)",
    "url": "https://bbs.ruliweb.com/community/board/300143/read/75435224?",
    "thumb": null,
    "score": 0,
    "views": 35,
    "crawled_at": "2026-06-04T03:28:52.609300+00:00"
  },
  {
    "id": "3836786021",
    "site": "theqoo",
    "title": "[스퀘어게시판 정치 카테고리 추가 및 정치 제외 기능 추가]",
    "url": "https://theqoo.net/square/3836786021",
    "thumb": null,
    "score": 0,
    "views": null,
    "crawled_at": "2026-06-04T03:28:52.609300+00:00"
  },
  {
    "id": "1638396273",
    "site": "theqoo",
    "title": "나는 더쿠에서 움짤을 한 번이라도 올려본 적이 있다 🙋‍♀️",
    "url": "https://theqoo.net/square/1638396273",
    "thumb": null,
    "score": 0,
    "views": null,
    "crawled_at": "2026-06-04T03:28:52.609300+00:00"
  },
  {
    "id": "1419228502",
    "site": "theqoo",
    "title": "더쿠에 쉽게 동영상을 올려보자 !",
    "url": "https://theqoo.net/square/1419228502",
    "thumb": null,
    "score": 0,
    "views": null,
    "crawled_at": "2026-06-04T03:28:52.609300+00:00"
  },
  {
    "id": "1386342829",
    "site": "theqoo",
    "title": "슬기로운 더쿠생활 : 더쿠 이용팁",
    "url": "https://theqoo.net/square/1386342829",
    "thumb": null,
    "score": 0,
    "views": null,
    "crawled_at": "2026-06-04T03:28:52.609300+00:00"
  },
  {
    "id": "9966419",
    "site": "ppomppu",
    "title": "오세훈 아직 한발 남은거 아니가요",
    "url": "https://www.ppomppu.co.kr/zboard/view.php?id=freeboard&page=1&divpage=1861&no=9966419",
    "thumb": null,
    "score": 0,
    "views": null,
    "crawled_at": "2026-06-04T03:28:52.609300+00:00"
  },
  {
    "id": "9966418",
    "site": "ppomppu",
    "title": "ㅋㅋ 서울시장 후보",
    "url": "https://www.ppomppu.co.kr/zboard/view.php?id=freeboard&page=1&divpage=1861&no=9966418",
    "thumb": null,
    "score": 0,
    "views": null,
    "crawled_at": "2026-06-04T03:28:52.609300+00:00"
  },
  {
    "id": "9966417",
    "site": "ppomppu",
    "title": "다음 총선 생각하면 지금이 싼값일수도요",
    "url": "https://www.ppomppu.co.kr/zboard/view.php?id=freeboard&page=1&divpage=1861&no=9966417",
    "thumb": null,
    "score": 0,
    "views": null,
    "crawled_at": "2026-06-04T03:28:52.609300+00:00"
  },
  {
    "id": "9966415",
    "site": "ppomppu",
    "title": "오세훈이가 괜히 5전5승한게 아닌게 똥오줌 분간 확실함",
    "url": "https://www.ppomppu.co.kr/zboard/view.php?id=freeboard&page=1&divpage=1861&no=9966415",
    "thumb": null,
    "score": 0,
    "views": null,
    "crawled_at": "2026-06-04T03:28:52.609300+00:00"
  },
  {
    "id": "9966414",
    "site": "ppomppu",
    "title": "신한 럭키박스 아직 안뜬건가요?",
    "url": "https://www.ppomppu.co.kr/zboard/view.php?id=freeboard&page=1&divpage=1861&no=9966414",
    "thumb": null,
    "score": 0,
    "views": null,
    "crawled_at": "2026-06-04T03:28:52.609300+00:00"
  },
  {
    "id": "9966413",
    "site": "ppomppu",
    "title": "20~30대 혜택 많이 받는다고 하는데요 ㅋㅋ",
    "url": "https://www.ppomppu.co.kr/zboard/view.php?id=freeboard&page=1&divpage=1861&no=9966413",
    "thumb": null,
    "score": 0,
    "views": null,
    "crawled_at": "2026-06-04T03:28:52.609300+00:00"
  },
  {
    "id": "9966412",
    "site": "ppomppu",
    "title": "백제 전성기",
    "url": "https://www.ppomppu.co.kr/zboard/view.php?id=freeboard&page=1&divpage=1861&no=9966412",
    "thumb": null,
    "score": 0,
    "views": null,
    "crawled_at": "2026-06-04T03:28:52.609300+00:00"
  },
  {
    "id": "9966409",
    "site": "ppomppu",
    "title": "홈플러스 결국 37개점 폐점 결정",
    "url": "https://www.ppomppu.co.kr/zboard/view.php?id=freeboard&page=1&divpage=1861&no=9966409",
    "thumb": null,
    "score": 0,
    "views": null,
    "crawled_at": "2026-06-04T03:28:52.609300+00:00"
  },
  {
    "id": "9966408",
    "site": "ppomppu",
    "title": "조국교수님으로 돌아가는건 어떤가 싶네요.",
    "url": "https://www.ppomppu.co.kr/zboard/view.php?id=freeboard&page=1&divpage=1861&no=9966408",
    "thumb": null,
    "score": 0,
    "views": null,
    "crawled_at": "2026-06-04T03:28:52.609300+00:00"
  },
  {
    "id": "9966406",
    "site": "ppomppu",
    "title": "서울 재투표하면 투표율 오를까요?",
    "url": "https://www.ppomppu.co.kr/zboard/view.php?id=freeboard&page=1&divpage=1861&no=9966406",
    "thumb": null,
    "score": 0,
    "views": null,
    "crawled_at": "2026-06-04T03:28:52.609300+00:00"
  },
  {
    "id": "9966405",
    "site": "ppomppu",
    "title": "충주시장 선거 표차",
    "url": "https://www.ppomppu.co.kr/zboard/view.php?id=freeboard&page=1&divpage=1861&no=9966405",
    "thumb": null,
    "score": 0,
    "views": null,
    "crawled_at": "2026-06-04T03:28:52.609300+00:00"
  },
  {
    "id": "9966403",
    "site": "ppomppu",
    "title": "재투표하자더니..",
    "url": "https://www.ppomppu.co.kr/zboard/view.php?id=freeboard&page=1&divpage=1861&no=9966403",
    "thumb": null,
    "score": 0,
    "views": null,
    "crawled_at": "2026-06-04T03:28:52.609300+00:00"
  },
  {
    "id": "9966402",
    "site": "ppomppu",
    "title": "대구 신공항 건설은 많이 어려워질 듯",
    "url": "https://www.ppomppu.co.kr/zboard/view.php?id=freeboard&page=1&divpage=1861&no=9966402",
    "thumb": null,
    "score": 0,
    "views": null,
    "crawled_at": "2026-06-04T03:28:52.609300+00:00"
  },
  {
    "id": "9966401",
    "site": "ppomppu",
    "title": "이게 다 인스타에 올라오는 화려한 삶을 동경하고 부러워하면서 생긱는 폐해라고...",
    "url": "https://www.ppomppu.co.kr/zboard/view.php?id=freeboard&page=1&divpage=1861&no=9966401",
    "thumb": null,
    "score": 0,
    "views": null,
    "crawled_at": "2026-06-04T03:28:52.609300+00:00"
  }
]