[
  {
    "id": "4218703806",
    "site": "theqoo",
    "title": "돌판 역대급 참담한 사건인데 기소조차 되지않아서 많은사람들의 관심이 필요한 사건",
    "url": "https://theqoo.net/square/4218703806",
    "thumb": null,
    "score": 1930,
    "views": null,
    "crawled_at": "2026-05-26T18:21:33.270887+00:00"
  },
  {
    "id": "4218703938",
    "site": "theqoo",
    "title": "[공식] 톱모델 최소라, 엄마된다..샤넬 런웨이서 D라인 공개 \"임신 맞아\"",
    "url": "https://theqoo.net/square/4218703938",
    "thumb": null,
    "score": 1823,
    "views": null,
    "crawled_at": "2026-05-26T18:21:33.270887+00:00"
  },
  {
    "id": "4218702221",
    "site": "theqoo",
    "title": "잠옷 며칠 입고 빨아야 할까…전문가들이 꼽은 ‘마지노선’[건강팩트체크]",
    "url": "https://theqoo.net/square/4218702221",
    "thumb": null,
    "score": 1808,
    "views": null,
    "crawled_at": "2026-05-26T18:21:33.270887+00:00"
  },
  {
    "id": "4218707469",
    "site": "theqoo",
    "title": "단추풀고시계풀고 자기 만져달라고 꼬시는거 미치셧나진짜",
    "url": "https://theqoo.net/square/4218707469",
    "thumb": null,
    "score": 1313,
    "views": null,
    "crawled_at": "2026-05-26T18:21:33.270887+00:00"
  },
  {
    "id": "4218705908",
    "site": "theqoo",
    "title": "덜 똑똑한 사람이 부자가 되는 이유",
    "url": "https://theqoo.net/square/4218705908",
    "thumb": null,
    "score": 1241,
    "views": null,
    "crawled_at": "2026-05-26T18:21:33.270887+00:00"
  },
  {
    "id": "4218707179",
    "site": "theqoo",
    "title": "싱어게인 우승하고 콘서트까지 꽉 채우고있는 가수 근황.jpg",
    "url": "https://theqoo.net/square/4218707179",
    "thumb": null,
    "score": 979,
    "views": null,
    "crawled_at": "2026-05-26T18:21:33.270887+00:00"
  },
  {
    "id": "4218709163",
    "site": "theqoo",
    "title": "현 정부의 국가정보국 신설에 반대하는 시위중인 일본인들",
    "url": "https://theqoo.net/square/4218709163",
    "thumb": null,
    "score": 631,
    "views": null,
    "crawled_at": "2026-05-26T18:21:33.270887+00:00"
  },
  {
    "id": "4218706991",
    "site": "theqoo",
    "title": "아니 남자한명 왜 계속 응원법에 추임새를 넣는거임?ㅠㅜ 개웃기네ㅋㅋㅋㅋ",
    "url": "https://theqoo.net/square/4218706991",
    "thumb": null,
    "score": 608,
    "views": null,
    "crawled_at": "2026-05-26T18:21:33.270887+00:00"
  },
  {
    "id": "4218707796",
    "site": "theqoo",
    "title": "어떤 이야기는 들어도 들어도 안 질리는데 본헤이터즈 탄생 비화가 그럼",
    "url": "https://theqoo.net/square/4218707796",
    "thumb": null,
    "score": 528,
    "views": null,
    "crawled_at": "2026-05-26T18:21:33.270887+00:00"
  },
  {
    "id": "4218706222",
    "site": "theqoo",
    "title": "탄수화물 월드컵",
    "url": "https://theqoo.net/square/4218706222",
    "thumb": null,
    "score": 366,
    "views": null,
    "crawled_at": "2026-05-26T18:21:33.270887+00:00"
  },
  {
    "id": "4218703779",
    "site": "theqoo",
    "title": "극한직업 인어",
    "url": "https://theqoo.net/square/4218703779",
    "thumb": null,
    "score": 333,
    "views": null,
    "crawled_at": "2026-05-26T18:21:33.270887+00:00"
  },
  {
    "id": "300143",
    "site": "ruliweb",
    "title": "차단 관리 수정 사항.",
    "url": "https://bbs.ruliweb.com/community/board/300143/read/75326722?",
    "thumb": null,
    "score": 256,
    "views": 23381,
    "crawled_at": "2026-05-26T18:21:33.270887+00:00"
  },
  {
    "id": "4218710793",
    "site": "theqoo",
    "title": "??? 원랜 서로 바뀌어야 하는 거 아니야?",
    "url": "https://theqoo.net/square/4218710793",
    "thumb": null,
    "score": 250,
    "views": null,
    "crawled_at": "2026-05-26T18:21:33.270887+00:00"
  },
  {
    "id": "4218706865",
    "site": "theqoo",
    "title": "자신만의 비밀 보물창고를 보여주는 꼬마아이",
    "url": "https://theqoo.net/square/4218706865",
    "thumb": null,
    "score": 249,
    "views": null,
    "crawled_at": "2026-05-26T18:21:33.270887+00:00"
  },
  {
    "id": "4218705751",
    "site": "theqoo",
    "title": "⊹˚₊신비로 가득 찬 행복의 가게로 오세요 무엇을 갖고 싶으세요?⊹˚₊",
    "url": "https://theqoo.net/square/4218705751",
    "thumb": null,
    "score": 240,
    "views": null,
    "crawled_at": "2026-05-26T18:21:33.270887+00:00"
  },
  {
    "id": "300143",
    "site": "ruliweb",
    "title": "Ai 필터 기능에 대해서",
    "url": "https://bbs.ruliweb.com/community/board/300143/read/75323558?",
    "thumb": null,
    "score": 185,
    "views": 17363,
    "crawled_at": "2026-05-26T18:21:33.270887+00:00"
  },
  {
    "id": "4218702930",
    "site": "theqoo",
    "title": "김재중 일본 디지털 싱글 ‘OASIS’ 발매",
    "url": "https://theqoo.net/square/4218702930",
    "thumb": null,
    "score": 90,
    "views": null,
    "crawled_at": "2026-05-26T18:21:33.270887+00:00"
  },
  {
    "id": "4218711680",
    "site": "theqoo",
    "title": "촬영이 즐거운 PD",
    "url": "https://theqoo.net/square/4218711680",
    "thumb": null,
    "score": 77,
    "views": null,
    "crawled_at": "2026-05-26T18:21:33.270887+00:00"
  },
  {
    "id": "300143",
    "site": "ruliweb",
    "title": "모르는 일본 유튜버가 한국어 설명해주는 영상이 갑자기 알고리즘에 떳다.(5)",
    "url": "https://bbs.ruliweb.com/community/board/300143/read/75334187?",
    "thumb": null,
    "score": 15,
    "views": 528,
    "crawled_at": "2026-05-26T18:21:33.270887+00:00"
  },
  {
    "id": "9951452",
    "site": "ppomppu",
    "title": "민주당에 화난 지지자.txt",
    "url": "https://www.ppomppu.co.kr/zboard/view.php?id=freeboard&page=1&divpage=1858&no=9951452",
    "thumb": null,
    "score": 8,
    "views": null,
    "crawled_at": "2026-05-26T18:21:33.270887+00:00"
  },
  {
    "id": "300142",
    "site": "ruliweb",
    "title": "듀얼센스 자가수리 중 구리선 절단",
    "url": "https://bbs.ruliweb.com/community/board/300142/read/30619465",
    "thumb": null,
    "score": 5,
    "views": 6845,
    "crawled_at": "2026-05-26T18:21:33.270887+00:00"
  },
  {
    "id": "300143",
    "site": "ruliweb",
    "title": "\"비추력을 10억까지 모으면 소원을 빌 수 있다는 전설이 있었다.\"(3)",
    "url": "https://bbs.ruliweb.com/community/board/300143/read/75334186?",
    "thumb": null,
    "score": 5,
    "views": 91,
    "crawled_at": "2026-05-26T18:21:33.270887+00:00"
  },
  {
    "id": "9951457",
    "site": "ppomppu",
    "title": "폴란드가 확인시켜준 천무 정확도",
    "url": "https://www.ppomppu.co.kr/zboard/view.php?id=freeboard&page=1&divpage=1858&no=9951457",
    "thumb": null,
    "score": 4,
    "views": null,
    "crawled_at": "2026-05-26T18:21:33.270887+00:00"
  },
  {
    "id": "185438",
    "site": "ruliweb",
    "title": "혹시 이번 이벤트 참가 늦게 하면 손실이 큰가요",
    "url": "https://bbs.ruliweb.com/etcs/board/185438/read/1395795",
    "thumb": null,
    "score": 2,
    "views": 383,
    "crawled_at": "2026-05-26T18:21:33.270887+00:00"
  },
  {
    "id": "300143",
    "site": "ruliweb",
    "title": "1부리그 승격에 성공해서 한탄하는 축구 감독(2)",
    "url": "https://bbs.ruliweb.com/community/board/300143/read/75334188?",
    "thumb": null,
    "score": 2,
    "views": 73,
    "crawled_at": "2026-05-26T18:21:33.270887+00:00"
  },
  {
    "id": "9951460",
    "site": "ppomppu",
    "title": "취중 연필 손 글씨 ㄷㄷ",
    "url": "https://www.ppomppu.co.kr/zboard/view.php?id=freeboard&page=1&divpage=1858&no=9951460",
    "thumb": null,
    "score": 2,
    "views": null,
    "crawled_at": "2026-05-26T18:21:33.270887+00:00"
  },
  {
    "id": "300143",
    "site": "ruliweb",
    "title": "죠땟다(2)",
    "url": "https://bbs.ruliweb.com/community/board/300143/read/75334194?",
    "thumb": null,
    "score": 1,
    "views": 32,
    "crawled_at": "2026-05-26T18:21:33.270887+00:00"
  },
  {
    "id": "300143",
    "site": "ruliweb",
    "title": "와 씨 방구 5초 동안 나옴(5)",
    "url": "https://bbs.ruliweb.com/community/board/300143/read/75334193?",
    "thumb": null,
    "score": 1,
    "views": 69,
    "crawled_at": "2026-05-26T18:21:33.270887+00:00"
  },
  {
    "id": "300143",
    "site": "ruliweb",
    "title": "잘생긴 외모 덕에 결혼한 개그맨(3)",
    "url": "https://bbs.ruliweb.com/community/board/300143/read/75334192?",
    "thumb": null,
    "score": 1,
    "views": 140,
    "crawled_at": "2026-05-26T18:21:33.270887+00:00"
  },
  {
    "id": "9951468",
    "site": "ppomppu",
    "title": "조선왕조실록에 언급되있는 일본국의 최동북단 영주와 아이누인.",
    "url": "https://www.ppomppu.co.kr/zboard/view.php?id=freeboard&page=1&divpage=1858&no=9951468",
    "thumb": null,
    "score": 1,
    "views": null,
    "crawled_at": "2026-05-26T18:21:33.270887+00:00"
  },
  {
    "id": "9951462",
    "site": "ppomppu",
    "title": "플레이스테이션 플러스 할인기간",
    "url": "https://www.ppomppu.co.kr/zboard/view.php?id=freeboard&page=1&divpage=1858&no=9951462",
    "thumb": null,
    "score": 1,
    "views": null,
    "crawled_at": "2026-05-26T18:21:33.270887+00:00"
  },
  {
    "id": "9951456",
    "site": "ppomppu",
    "title": "EBS 극한직업 먹방 모음",
    "url": "https://www.ppomppu.co.kr/zboard/view.php?id=freeboard&page=1&divpage=1858&no=9951456",
    "thumb": null,
    "score": 1,
    "views": null,
    "crawled_at": "2026-05-26T18:21:33.270887+00:00"
  },
  {
    "id": "9951453",
    "site": "ppomppu",
    "title": "창업주 관련 한번 보니 알고리즘 계속 나오네요",
    "url": "https://www.ppomppu.co.kr/zboard/view.php?id=freeboard&page=1&divpage=1858&no=9951453",
    "thumb": null,
    "score": 1,
    "views": null,
    "crawled_at": "2026-05-26T18:21:33.270887+00:00"
  },
  {
    "id": "9951451",
    "site": "ppomppu",
    "title": "천연가죽 소파 원래 이런가요?",
    "url": "https://www.ppomppu.co.kr/zboard/view.php?id=freeboard&page=1&divpage=1858&no=9951451",
    "thumb": null,
    "score": 1,
    "views": null,
    "crawled_at": "2026-05-26T18:21:33.270887+00:00"
  },
  {
    "id": "10",
    "site": "ruliweb",
    "title": "계정 도용 방지를 위해 비번을 변경해주세요.",
    "url": "https://bbs.ruliweb.com/etcs/board/10/read/151",
    "thumb": null,
    "score": 0,
    "views": null,
    "crawled_at": "2026-05-26T18:21:33.270887+00:00"
  },
  {
    "id": "185595",
    "site": "ruliweb",
    "title": "기계일꾼 제가 이 상태인데...",
    "url": "https://bbs.ruliweb.com/etcs/board/185595/read/14664",
    "thumb": null,
    "score": 0,
    "views": 334,
    "crawled_at": "2026-05-26T18:21:33.270887+00:00"
  },
  {
    "id": "300143",
    "site": "ruliweb",
    "title": "(히로아카) 히로아카가 최고의 만화는 아니었지만",
    "url": "https://bbs.ruliweb.com/community/board/300143/read/75334199?",
    "thumb": null,
    "score": 0,
    "views": 4,
    "crawled_at": "2026-05-26T18:21:33.270887+00:00"
  },
  {
    "id": "300143",
    "site": "ruliweb",
    "title": "호이4) 다음 dlc 인도네시아도 좀 개편 하나보네",
    "url": "https://bbs.ruliweb.com/community/board/300143/read/75334198?",
    "thumb": null,
    "score": 0,
    "views": 2,
    "crawled_at": "2026-05-26T18:21:33.270887+00:00"
  },
  {
    "id": "300143",
    "site": "ruliweb",
    "title": "건담) 중딩때 만들었던 더블오 흐지들 꺼내봤는데",
    "url": "https://bbs.ruliweb.com/community/board/300143/read/75334197?",
    "thumb": null,
    "score": 0,
    "views": 2,
    "crawled_at": "2026-05-26T18:21:33.270887+00:00"
  },
  {
    "id": "300143",
    "site": "ruliweb",
    "title": "설정 논란 간단하게 해결하는법",
    "url": "https://bbs.ruliweb.com/community/board/300143/read/75334196?",
    "thumb": null,
    "score": 0,
    "views": 7,
    "crawled_at": "2026-05-26T18:21:33.270887+00:00"
  },
  {
    "id": "300143",
    "site": "ruliweb",
    "title": "블루아카) 데카그라마톤 2장 다 봤다",
    "url": "https://bbs.ruliweb.com/community/board/300143/read/75334195?",
    "thumb": null,
    "score": 0,
    "views": 31,
    "crawled_at": "2026-05-26T18:21:33.270887+00:00"
  },
  {
    "id": "300143",
    "site": "ruliweb",
    "title": "폴드에서 유게하기 점점 불편해지네",
    "url": "https://bbs.ruliweb.com/community/board/300143/read/75334191?",
    "thumb": null,
    "score": 0,
    "views": 56,
    "crawled_at": "2026-05-26T18:21:33.270887+00:00"
  },
  {
    "id": "300143",
    "site": "ruliweb",
    "title": "컴퓨터에 모니터 2대 연결하려는데 질문점(4)",
    "url": "https://bbs.ruliweb.com/community/board/300143/read/75334190?",
    "thumb": null,
    "score": 0,
    "views": 71,
    "crawled_at": "2026-05-26T18:21:33.270887+00:00"
  },
  {
    "id": "300143",
    "site": "ruliweb",
    "title": "오래간만에 먹은 피자헛은 몬가 몬가였다...(1)",
    "url": "https://bbs.ruliweb.com/community/board/300143/read/75334189?",
    "thumb": null,
    "score": 0,
    "views": 64,
    "crawled_at": "2026-05-26T18:21:33.270887+00:00"
  },
  {
    "id": "3836786021",
    "site": "theqoo",
    "title": "[스퀘어게시판 정치 카테고리 추가 및 정치 제외 기능 추가]",
    "url": "https://theqoo.net/square/3836786021",
    "thumb": null,
    "score": 0,
    "views": null,
    "crawled_at": "2026-05-26T18:21:33.270887+00:00"
  },
  {
    "id": "1638396273",
    "site": "theqoo",
    "title": "나는 더쿠에서 움짤을 한 번이라도 올려본 적이 있다 🙋‍♀️",
    "url": "https://theqoo.net/square/1638396273",
    "thumb": null,
    "score": 0,
    "views": null,
    "crawled_at": "2026-05-26T18:21:33.270887+00:00"
  },
  {
    "id": "1419228502",
    "site": "theqoo",
    "title": "더쿠에 쉽게 동영상을 올려보자 !",
    "url": "https://theqoo.net/square/1419228502",
    "thumb": null,
    "score": 0,
    "views": null,
    "crawled_at": "2026-05-26T18:21:33.270887+00:00"
  },
  {
    "id": "1386342829",
    "site": "theqoo",
    "title": "슬기로운 더쿠생활 : 더쿠 이용팁",
    "url": "https://theqoo.net/square/1386342829",
    "thumb": null,
    "score": 0,
    "views": null,
    "crawled_at": "2026-05-26T18:21:33.270887+00:00"
  },
  {
    "id": "9951469",
    "site": "ppomppu",
    "title": "오늘도 반도체 회사들 주가 떡상",
    "url": "https://www.ppomppu.co.kr/zboard/view.php?id=freeboard&page=1&divpage=1858&no=9951469",
    "thumb": null,
    "score": 0,
    "views": null,
    "crawled_at": "2026-05-26T18:21:33.270887+00:00"
  },
  {
    "id": "9951467",
    "site": "ppomppu",
    "title": "요즘 극우들 미쳐날뛰네요",
    "url": "https://www.ppomppu.co.kr/zboard/view.php?id=freeboard&page=1&divpage=1858&no=9951467",
    "thumb": null,
    "score": 0,
    "views": null,
    "crawled_at": "2026-05-26T18:21:33.270887+00:00"
  },
  {
    "id": "9951466",
    "site": "ppomppu",
    "title": "보기 보단 맛있는 음식 jpg",
    "url": "https://www.ppomppu.co.kr/zboard/view.php?id=freeboard&page=1&divpage=1858&no=9951466",
    "thumb": null,
    "score": 0,
    "views": null,
    "crawled_at": "2026-05-26T18:21:33.270887+00:00"
  },
  {
    "id": "9951465",
    "site": "ppomppu",
    "title": "고조선의 번영에 대한 가장 대표적인 기록.",
    "url": "https://www.ppomppu.co.kr/zboard/view.php?id=freeboard&page=1&divpage=1858&no=9951465",
    "thumb": null,
    "score": 0,
    "views": null,
    "crawled_at": "2026-05-26T18:21:33.270887+00:00"
  },
  {
    "id": "9951464",
    "site": "ppomppu",
    "title": "평택을 주민분들의 선택이 궁금하긴 하네요..",
    "url": "https://www.ppomppu.co.kr/zboard/view.php?id=freeboard&page=1&divpage=1858&no=9951464",
    "thumb": null,
    "score": 0,
    "views": null,
    "crawled_at": "2026-05-26T18:21:33.270887+00:00"
  },
  {
    "id": "9951463",
    "site": "ppomppu",
    "title": "자동차로 음식배달 알바하시는분들은 뭐가 남긴할까요?",
    "url": "https://www.ppomppu.co.kr/zboard/view.php?id=freeboard&page=1&divpage=1858&no=9951463",
    "thumb": null,
    "score": 0,
    "views": null,
    "crawled_at": "2026-05-26T18:21:33.270887+00:00"
  },
  {
    "id": "9951461",
    "site": "ppomppu",
    "title": "[지선]한달 전 쯤에 지인이 단톡방에 이 짤을 투척하면서",
    "url": "https://www.ppomppu.co.kr/zboard/view.php?id=freeboard&page=1&divpage=1858&no=9951461",
    "thumb": null,
    "score": 0,
    "views": null,
    "crawled_at": "2026-05-26T18:21:33.270887+00:00"
  },
  {
    "id": "9951459",
    "site": "ppomppu",
    "title": "2026년 5월 26일 국내 박스오피스",
    "url": "https://www.ppomppu.co.kr/zboard/view.php?id=freeboard&page=1&divpage=1858&no=9951459",
    "thumb": null,
    "score": 0,
    "views": null,
    "crawled_at": "2026-05-26T18:21:33.270887+00:00"
  },
  {
    "id": "9951458",
    "site": "ppomppu",
    "title": "네이버 오늘 배송!!",
    "url": "https://www.ppomppu.co.kr/zboard/view.php?id=freeboard&page=1&divpage=1858&no=9951458",
    "thumb": null,
    "score": 0,
    "views": null,
    "crawled_at": "2026-05-26T18:21:33.270887+00:00"
  },
  {
    "id": "9951455",
    "site": "ppomppu",
    "title": "내일 장 시작하자마자 구매 되게 하려면",
    "url": "https://www.ppomppu.co.kr/zboard/view.php?id=freeboard&page=1&divpage=1858&no=9951455",
    "thumb": null,
    "score": 0,
    "views": null,
    "crawled_at": "2026-05-26T18:21:33.270887+00:00"
  },
  {
    "id": "9951454",
    "site": "ppomppu",
    "title": "(외지주)박진영의 퇴장이 아쉽기만 합니다..",
    "url": "https://www.ppomppu.co.kr/zboard/view.php?id=freeboard&page=1&divpage=1858&no=9951454",
    "thumb": null,
    "score": 0,
    "views": null,
    "crawled_at": "2026-05-26T18:21:33.270887+00:00"
  },
  {
    "id": "9951450",
    "site": "ppomppu",
    "title": "라스트 콘서트 ost - 유투브",
    "url": "https://www.ppomppu.co.kr/zboard/view.php?id=freeboard&page=1&divpage=1858&no=9951450",
    "thumb": null,
    "score": 0,
    "views": null,
    "crawled_at": "2026-05-26T18:21:33.270887+00:00"
  }
]