[
  {
    "id": "4215827571",
    "site": "theqoo",
    "title": "승려로써 분명히 말하지만 인생은 별다른 예고 없이 갑자기 끝납니다",
    "url": "https://theqoo.net/square/4215827571",
    "thumb": null,
    "score": 1580,
    "views": null,
    "crawled_at": "2026-05-24T13:12:39.912630+00:00"
  },
  {
    "id": "4215821712",
    "site": "theqoo",
    "title": "아이오아이 '갑자기' 멜론 탑백 10위 (🔺3 ) 피크",
    "url": "https://theqoo.net/square/4215821712",
    "thumb": null,
    "score": 835,
    "views": null,
    "crawled_at": "2026-05-24T13:12:39.912630+00:00"
  },
  {
    "id": "4215827438",
    "site": "theqoo",
    "title": "사육사한테 안아달라고 하는 코알라🐨",
    "url": "https://theqoo.net/square/4215827438",
    "thumb": null,
    "score": 637,
    "views": null,
    "crawled_at": "2026-05-24T13:12:39.912630+00:00"
  },
  {
    "id": "4215826419",
    "site": "theqoo",
    "title": "최민식 대본리딩 수준",
    "url": "https://theqoo.net/square/4215826419",
    "thumb": null,
    "score": 631,
    "views": null,
    "crawled_at": "2026-05-24T13:12:39.912630+00:00"
  },
  {
    "id": "4215827298",
    "site": "theqoo",
    "title": "마지막으로 걱정과 불안 없이 잠을 잤던 때의 내 사진",
    "url": "https://theqoo.net/square/4215827298",
    "thumb": null,
    "score": 575,
    "views": null,
    "crawled_at": "2026-05-24T13:12:39.912630+00:00"
  },
  {
    "id": "4215832584",
    "site": "theqoo",
    "title": "이번주도 ㄹㅇ 중소의 기적 수준으로 감다살이었던.. 빌리 WORK 2주차 의상.jpg",
    "url": "https://theqoo.net/square/4215832584",
    "thumb": null,
    "score": 548,
    "views": null,
    "crawled_at": "2026-05-24T13:12:39.912630+00:00"
  },
  {
    "id": "4215826906",
    "site": "theqoo",
    "title": "한머리 두냄새",
    "url": "https://theqoo.net/square/4215826906",
    "thumb": null,
    "score": 497,
    "views": null,
    "crawled_at": "2026-05-24T13:12:39.912630+00:00"
  },
  {
    "id": "4215824686",
    "site": "theqoo",
    "title": "호랑이 키우시는건가요?",
    "url": "https://theqoo.net/square/4215824686",
    "thumb": null,
    "score": 451,
    "views": null,
    "crawled_at": "2026-05-24T13:12:39.912630+00:00"
  },
  {
    "id": "4215835841",
    "site": "theqoo",
    "title": "일본에서 화제인 앉아서 공부하는 편의점 알바생",
    "url": "https://theqoo.net/square/4215835841",
    "thumb": null,
    "score": 426,
    "views": null,
    "crawled_at": "2026-05-24T13:12:39.912630+00:00"
  },
  {
    "id": "4215836137",
    "site": "theqoo",
    "title": "군체 잘 본 사람도 잘 안 본 사람도 대체적으로 공감하는 이야기",
    "url": "https://theqoo.net/square/4215836137",
    "thumb": null,
    "score": 284,
    "views": null,
    "crawled_at": "2026-05-24T13:12:39.912630+00:00"
  },
  {
    "id": "4215838491",
    "site": "theqoo",
    "title": "예전에 아파트 계단 물청소하던거 기억나는 사람",
    "url": "https://theqoo.net/square/4215838491",
    "thumb": null,
    "score": 276,
    "views": null,
    "crawled_at": "2026-05-24T13:12:39.912630+00:00"
  },
  {
    "id": "4215835518",
    "site": "theqoo",
    "title": "[꽃청춘] 박서준: 누나 공주니까?",
    "url": "https://theqoo.net/square/4215835518",
    "thumb": null,
    "score": 256,
    "views": null,
    "crawled_at": "2026-05-24T13:12:39.912630+00:00"
  },
  {
    "id": "4215837615",
    "site": "theqoo",
    "title": "\"주면 무조건 두 배로 받는다\"…이세희도 놀란 임지연의 '역대급' 통 큰 면모 ('미우새')",
    "url": "https://theqoo.net/square/4215837615",
    "thumb": null,
    "score": 198,
    "views": null,
    "crawled_at": "2026-05-24T13:12:39.912630+00:00"
  },
  {
    "id": "4215838324",
    "site": "theqoo",
    "title": "일본 최초로 칸 영화제 여우주연상 이라는 오카모토 타오",
    "url": "https://theqoo.net/square/4215838324",
    "thumb": null,
    "score": 144,
    "views": null,
    "crawled_at": "2026-05-24T13:12:39.912630+00:00"
  },
  {
    "id": "4215837983",
    "site": "theqoo",
    "title": "아이실드21, 원펀맨 리메이크 그림 작가 무라타 유스케 근황...twt",
    "url": "https://theqoo.net/square/4215837983",
    "thumb": null,
    "score": 111,
    "views": null,
    "crawled_at": "2026-05-24T13:12:39.912630+00:00"
  },
  {
    "id": "4215828559",
    "site": "theqoo",
    "title": "ITZY (있지) \"Motto\" Dance Video (Rooftop Ver.)  COMING SOON",
    "url": "https://theqoo.net/square/4215828559",
    "thumb": null,
    "score": 97,
    "views": null,
    "crawled_at": "2026-05-24T13:12:39.912630+00:00"
  },
  {
    "id": "9948952",
    "site": "ppomppu",
    "title": "맥주 안쥬",
    "url": "https://www.ppomppu.co.kr/zboard/view.php?id=freeboard&page=1&divpage=1858&no=9948952",
    "thumb": null,
    "score": 4,
    "views": null,
    "crawled_at": "2026-05-24T13:12:39.912630+00:00"
  },
  {
    "id": "9948949",
    "site": "ppomppu",
    "title": "고일석 기자 페이스북에 올라온 흥미로운 글",
    "url": "https://www.ppomppu.co.kr/zboard/view.php?id=freeboard&page=1&divpage=1858&no=9948949",
    "thumb": null,
    "score": 4,
    "views": null,
    "crawled_at": "2026-05-24T13:12:39.912630+00:00"
  },
  {
    "id": "300143",
    "site": "ruliweb",
    "title": "요즘 신차에 꼽혀서 자동차 유투버들 영상 보고있는데",
    "url": "https://bbs.ruliweb.com/community/board/300143/read/75305307?",
    "thumb": null,
    "score": 2,
    "views": 23,
    "crawled_at": "2026-05-24T13:12:39.912630+00:00"
  },
  {
    "id": "9948957",
    "site": "ppomppu",
    "title": "김용남 누가 공천하거나 추천햇을까요?",
    "url": "https://www.ppomppu.co.kr/zboard/view.php?id=freeboard&page=1&divpage=1858&no=9948957",
    "thumb": null,
    "score": 2,
    "views": null,
    "crawled_at": "2026-05-24T13:12:39.912630+00:00"
  },
  {
    "id": "300142",
    "site": "ruliweb",
    "title": "취미용(도색) 아크릴 물감 쉴드에픽 vs 조소냐",
    "url": "https://bbs.ruliweb.com/community/board/300142/read/30619460",
    "thumb": null,
    "score": 1,
    "views": 1468,
    "crawled_at": "2026-05-24T13:12:39.912630+00:00"
  },
  {
    "id": "185062",
    "site": "ruliweb",
    "title": "명토 불멸맹약 조건 뭔지 아시나요?",
    "url": "https://bbs.ruliweb.com/etcs/board/185062/read/173221",
    "thumb": null,
    "score": 1,
    "views": 130,
    "crawled_at": "2026-05-24T13:12:39.912630+00:00"
  },
  {
    "id": "9948963",
    "site": "ppomppu",
    "title": "일베만큼 정리해야 될 게 부포죠",
    "url": "https://www.ppomppu.co.kr/zboard/view.php?id=freeboard&page=1&divpage=1858&no=9948963",
    "thumb": null,
    "score": 1,
    "views": null,
    "crawled_at": "2026-05-24T13:12:39.912630+00:00"
  },
  {
    "id": "9948960",
    "site": "ppomppu",
    "title": "장동혁 \"스타벅스 커피 들고 투표장 가자..이 정부민주당 심판\"",
    "url": "https://www.ppomppu.co.kr/zboard/view.php?id=freeboard&page=1&divpage=1858&no=9948960",
    "thumb": null,
    "score": 1,
    "views": null,
    "crawled_at": "2026-05-24T13:12:39.912630+00:00"
  },
  {
    "id": "100647",
    "site": "ruliweb",
    "title": "소유지의 개념이 정확히 뭔가요?",
    "url": "https://bbs.ruliweb.com/etcs/board/100647/read/9426236",
    "thumb": null,
    "score": 0,
    "views": 122,
    "crawled_at": "2026-05-24T13:12:39.912630+00:00"
  },
  {
    "id": "300143",
    "site": "ruliweb",
    "title": "좁은 길에서 어깨빵 당할 뻔할때.manga",
    "url": "https://bbs.ruliweb.com/community/board/300143/read/75305318?",
    "thumb": null,
    "score": 0,
    "views": 3,
    "crawled_at": "2026-05-24T13:12:39.912630+00:00"
  },
  {
    "id": "300143",
    "site": "ruliweb",
    "title": "프로세카)커플 할인.jpg",
    "url": "https://bbs.ruliweb.com/community/board/300143/read/75305317?",
    "thumb": null,
    "score": 0,
    "views": 2,
    "crawled_at": "2026-05-24T13:12:39.912630+00:00"
  },
  {
    "id": "300143",
    "site": "ruliweb",
    "title": "지제네 이터널)) 이거 스테미너가 ㅈㄴ 안차는구나",
    "url": "https://bbs.ruliweb.com/community/board/300143/read/75305316?",
    "thumb": null,
    "score": 0,
    "views": 1,
    "crawled_at": "2026-05-24T13:12:39.912630+00:00"
  },
  {
    "id": "300143",
    "site": "ruliweb",
    "title": "블리치) 히사기의 이 말이 어의없는 이유",
    "url": "https://bbs.ruliweb.com/community/board/300143/read/75305315?",
    "thumb": null,
    "score": 0,
    "views": 3,
    "crawled_at": "2026-05-24T13:12:39.912630+00:00"
  },
  {
    "id": "300143",
    "site": "ruliweb",
    "title": "감기에 걸린 소꿉친구 병문안 간 manhwa",
    "url": "https://bbs.ruliweb.com/community/board/300143/read/75305314?",
    "thumb": null,
    "score": 0,
    "views": 21,
    "crawled_at": "2026-05-24T13:12:39.912630+00:00"
  },
  {
    "id": "300143",
    "site": "ruliweb",
    "title": "버튜버] 친모아 커마로 크로니 만들려고 하나 보네",
    "url": "https://bbs.ruliweb.com/community/board/300143/read/75305313?",
    "thumb": null,
    "score": 0,
    "views": 5,
    "crawled_at": "2026-05-24T13:12:39.912630+00:00"
  },
  {
    "id": "300143",
    "site": "ruliweb",
    "title": "버튜버) \"친구에게 그림 홀로카 얘기 했더니 라이브 오고 싶다고 하더라구...",
    "url": "https://bbs.ruliweb.com/community/board/300143/read/75305312?",
    "thumb": null,
    "score": 0,
    "views": 5,
    "crawled_at": "2026-05-24T13:12:39.912630+00:00"
  },
  {
    "id": "300143",
    "site": "ruliweb",
    "title": "[소전2]스포)이건 좀 억울하네 ㅋㅋㅋㅋ",
    "url": "https://bbs.ruliweb.com/community/board/300143/read/75305311?",
    "thumb": null,
    "score": 0,
    "views": 5,
    "crawled_at": "2026-05-24T13:12:39.912630+00:00"
  },
  {
    "id": "300143",
    "site": "ruliweb",
    "title": "활협전) 상선세가는 대체 왜 그럼?",
    "url": "https://bbs.ruliweb.com/community/board/300143/read/75305310?",
    "thumb": null,
    "score": 0,
    "views": 8,
    "crawled_at": "2026-05-24T13:12:39.912630+00:00"
  },
  {
    "id": "300143",
    "site": "ruliweb",
    "title": "오늘 플레이 엑스포 던파 부스에서(1)",
    "url": "https://bbs.ruliweb.com/community/board/300143/read/75305309?",
    "thumb": null,
    "score": 0,
    "views": 9,
    "crawled_at": "2026-05-24T13:12:39.912630+00:00"
  },
  {
    "id": "300143",
    "site": "ruliweb",
    "title": "2026년 인터넷 문화 트랜드 자가체크.jpg",
    "url": "https://bbs.ruliweb.com/community/board/300143/read/75305308?",
    "thumb": null,
    "score": 0,
    "views": 18,
    "crawled_at": "2026-05-24T13:12:39.912630+00:00"
  },
  {
    "id": "300143",
    "site": "ruliweb",
    "title": "롤) \"안녕 Korea 친구들, 내일 쉬는 날이라며?\"",
    "url": "https://bbs.ruliweb.com/community/board/300143/read/75305306?",
    "thumb": null,
    "score": 0,
    "views": 54,
    "crawled_at": "2026-05-24T13:12:39.912630+00:00"
  },
  {
    "id": "300143",
    "site": "ruliweb",
    "title": "디아4 야만 했는데 무슨케릭으로 시작할까",
    "url": "https://bbs.ruliweb.com/community/board/300143/read/75305305?",
    "thumb": null,
    "score": 0,
    "views": 8,
    "crawled_at": "2026-05-24T13:12:39.912630+00:00"
  },
  {
    "id": "300143",
    "site": "ruliweb",
    "title": "버튜버)스이짱: 눈앞에 카구야가 있었다",
    "url": "https://bbs.ruliweb.com/community/board/300143/read/75305304?",
    "thumb": null,
    "score": 0,
    "views": 25,
    "crawled_at": "2026-05-24T13:12:39.912630+00:00"
  },
  {
    "id": "300143",
    "site": "ruliweb",
    "title": "난 학교라는 장소 자체에 로망이 있는데(2)",
    "url": "https://bbs.ruliweb.com/community/board/300143/read/75305303?",
    "thumb": null,
    "score": 0,
    "views": 26,
    "crawled_at": "2026-05-24T13:12:39.912630+00:00"
  },
  {
    "id": "300143",
    "site": "ruliweb",
    "title": "내 사후에 예비 공폰은 반드시 사라지게해야하는데(2)",
    "url": "https://bbs.ruliweb.com/community/board/300143/read/75305302?",
    "thumb": null,
    "score": 0,
    "views": 48,
    "crawled_at": "2026-05-24T13:12:39.912630+00:00"
  },
  {
    "id": "3836786021",
    "site": "theqoo",
    "title": "[스퀘어게시판 정치 카테고리 추가 및 정치 제외 기능 추가]",
    "url": "https://theqoo.net/square/3836786021",
    "thumb": null,
    "score": 0,
    "views": null,
    "crawled_at": "2026-05-24T13:12:39.912630+00:00"
  },
  {
    "id": "1638396273",
    "site": "theqoo",
    "title": "나는 더쿠에서 움짤을 한 번이라도 올려본 적이 있다 🙋‍♀️",
    "url": "https://theqoo.net/square/1638396273",
    "thumb": null,
    "score": 0,
    "views": null,
    "crawled_at": "2026-05-24T13:12:39.912630+00:00"
  },
  {
    "id": "1419228502",
    "site": "theqoo",
    "title": "더쿠에 쉽게 동영상을 올려보자 !",
    "url": "https://theqoo.net/square/1419228502",
    "thumb": null,
    "score": 0,
    "views": null,
    "crawled_at": "2026-05-24T13:12:39.912630+00:00"
  },
  {
    "id": "1386342829",
    "site": "theqoo",
    "title": "슬기로운 더쿠생활 : 더쿠 이용팁",
    "url": "https://theqoo.net/square/1386342829",
    "thumb": null,
    "score": 0,
    "views": null,
    "crawled_at": "2026-05-24T13:12:39.912630+00:00"
  },
  {
    "id": "9948969",
    "site": "ppomppu",
    "title": "'울산시장' 김상욱 37%김두겸 32%",
    "url": "https://www.ppomppu.co.kr/zboard/view.php?id=freeboard&page=1&divpage=1858&no=9948969",
    "thumb": null,
    "score": 0,
    "views": null,
    "crawled_at": "2026-05-24T13:12:39.912630+00:00"
  },
  {
    "id": "9948968",
    "site": "ppomppu",
    "title": "잘나가던 스타벅스가 민심을 잃은 이유.jpg",
    "url": "https://www.ppomppu.co.kr/zboard/view.php?id=freeboard&page=1&divpage=1858&no=9948968",
    "thumb": null,
    "score": 0,
    "views": null,
    "crawled_at": "2026-05-24T13:12:39.912630+00:00"
  },
  {
    "id": "9948967",
    "site": "ppomppu",
    "title": "한동훈 41.5%-하정우 34.5%-박민식 18.9%.요동치는 부산 북갑",
    "url": "https://www.ppomppu.co.kr/zboard/view.php?id=freeboard&page=1&divpage=1858&no=9948967",
    "thumb": null,
    "score": 0,
    "views": null,
    "crawled_at": "2026-05-24T13:12:39.912630+00:00"
  },
  {
    "id": "9948966",
    "site": "ppomppu",
    "title": "악마 이스라엘을 보니",
    "url": "https://www.ppomppu.co.kr/zboard/view.php?id=freeboard&page=1&divpage=1858&no=9948966",
    "thumb": null,
    "score": 0,
    "views": null,
    "crawled_at": "2026-05-24T13:12:39.912630+00:00"
  },
  {
    "id": "9948965",
    "site": "ppomppu",
    "title": "오늘 토트넘 강등되겠죠? ㄷㄷ",
    "url": "https://www.ppomppu.co.kr/zboard/view.php?id=freeboard&page=1&divpage=1858&no=9948965",
    "thumb": null,
    "score": 0,
    "views": null,
    "crawled_at": "2026-05-24T13:12:39.912630+00:00"
  },
  {
    "id": "9948964",
    "site": "ppomppu",
    "title": "나경원 \"쿠팡 다음 스타벅스..그 다음은 누구\" 두 번째 직격",
    "url": "https://www.ppomppu.co.kr/zboard/view.php?id=freeboard&page=1&divpage=1858&no=9948964",
    "thumb": null,
    "score": 0,
    "views": null,
    "crawled_at": "2026-05-24T13:12:39.912630+00:00"
  },
  {
    "id": "9948962",
    "site": "ppomppu",
    "title": "미국의 탈출한 거대한 돼지 생포 작전 ㄷ.avi",
    "url": "https://www.ppomppu.co.kr/zboard/view.php?id=freeboard&page=1&divpage=1858&no=9948962",
    "thumb": null,
    "score": 0,
    "views": null,
    "crawled_at": "2026-05-24T13:12:39.912630+00:00"
  },
  {
    "id": "9948961",
    "site": "ppomppu",
    "title": "56년전 인류가 달에 갔다온거 맞나요",
    "url": "https://www.ppomppu.co.kr/zboard/view.php?id=freeboard&page=1&divpage=1858&no=9948961",
    "thumb": null,
    "score": 0,
    "views": null,
    "crawled_at": "2026-05-24T13:12:39.912630+00:00"
  },
  {
    "id": "9948956",
    "site": "ppomppu",
    "title": "K-기밀 또 유출 ㄷㄷ..jpg",
    "url": "https://www.ppomppu.co.kr/zboard/view.php?id=freeboard&page=1&divpage=1858&no=9948956",
    "thumb": null,
    "score": 0,
    "views": null,
    "crawled_at": "2026-05-24T13:12:39.912630+00:00"
  },
  {
    "id": "9948955",
    "site": "ppomppu",
    "title": "지금 잉글랜드 축구 국가대표팀이 역대 최고 전력인가요?",
    "url": "https://www.ppomppu.co.kr/zboard/view.php?id=freeboard&page=1&divpage=1858&no=9948955",
    "thumb": null,
    "score": 0,
    "views": null,
    "crawled_at": "2026-05-24T13:12:39.912630+00:00"
  },
  {
    "id": "9948954",
    "site": "ppomppu",
    "title": "에버튼 팬들한테 환호성 보내는 아스날 팬들",
    "url": "https://www.ppomppu.co.kr/zboard/view.php?id=freeboard&page=1&divpage=1858&no=9948954",
    "thumb": null,
    "score": 0,
    "views": null,
    "crawled_at": "2026-05-24T13:12:39.912630+00:00"
  },
  {
    "id": "9948953",
    "site": "ppomppu",
    "title": "'부산 북갑' 한동훈 36%, 하정우 35%",
    "url": "https://www.ppomppu.co.kr/zboard/view.php?id=freeboard&page=1&divpage=1858&no=9948953",
    "thumb": null,
    "score": 0,
    "views": null,
    "crawled_at": "2026-05-24T13:12:39.912630+00:00"
  },
  {
    "id": "9948951",
    "site": "ppomppu",
    "title": "국정원의 모함일수도 있다",
    "url": "https://www.ppomppu.co.kr/zboard/view.php?id=freeboard&page=1&divpage=1858&no=9948951",
    "thumb": null,
    "score": 0,
    "views": null,
    "crawled_at": "2026-05-24T13:12:39.912630+00:00"
  },
  {
    "id": "9948950",
    "site": "ppomppu",
    "title": "색전술은 필수인가요..",
    "url": "https://www.ppomppu.co.kr/zboard/view.php?id=freeboard&page=1&divpage=1858&no=9948950",
    "thumb": null,
    "score": 0,
    "views": null,
    "crawled_at": "2026-05-24T13:12:39.912630+00:00"
  },
  {
    "id": "9948948",
    "site": "ppomppu",
    "title": "최근에 급증하고 있다는 신혼 이혼",
    "url": "https://www.ppomppu.co.kr/zboard/view.php?id=freeboard&page=1&divpage=1858&no=9948948",
    "thumb": null,
    "score": 0,
    "views": null,
    "crawled_at": "2026-05-24T13:12:39.912630+00:00"
  }
]